{
    "domain": "dantri.com.vn",
    "code": "b5939a392edca85dede97fb36a86ec2e97fef83d",
    "title": "Vẻ đẹp nghệ thuật nơi không gian công cộng trên khắp thế giới",
    "url": "http://dantri.com.vn/van-hoa/ve-dep-nghe-thuat-noi-khong-gian-cong-cong-tren-khap-the-gioi-20161128221155343.htm",
    "labels": "Dân trí/Văn hóa",
    "content": "\nDân trí Vẻ đẹp của không gian công cộng là điều mà tất cả các thành phố lớn trên thế giới đều hướng đến. Những triển lãm, sắp đặt nghệ thuật thường xuyên được thực hiện để tô điểm cho vẻ đẹp của không gian chung, đồng thời tạo nên những trải nghiệm mới mẻ cho người dân.\r\nHãy cùng chiêm ngưỡng vẻ đẹp nơi không gian công cộng ở một số thành phố lớn trên thế giới:                       Bích Ngọc\nTheo Boston Globe",
    "image_url": "https://dantri4.vcmedia.vn/zoom/80_50/7a7517334e/2016/11/28/1-1480309055750.jpg",
    "date": "2016-11-29, 02:00:00+00:00",
    "label_general": "Đời sống - Xã hội"
}