{
    "domain": "dantri.com.vn",
    "code": "a81e2fba972c0c8344ba291b7987bdef42dc2074",
    "title": "Danh sách ủng hộ tuần 3 tháng 10 năm 2016",
    "url": "http://dantri.com.vn/tam-long-nhan-ai/danh-sach-ung-ho-tuan-3-thang-10-nam-2016-20161026215524176.htm",
    "labels": "Dân trí/Tấm lòng nhân ái",
    "content": "\nDân trí Tuần qua, Quỹ Nhân ái - Báo điện tử Dân trí tiếp tục nhận được sự quan tâm, giúp đỡ của bạn đọc dành cho các cảnh đời kém may mắn. Tổng số tiền bạn đọc gửi về Quỹ trong tuần là: 899,637,990 đồng.\r\nNGÀYDIỄN GIẢISỐ TIỀN Bạn đọc ủng hộ tại Tòa soạn từ\n\t\t\tngày 16 đến 22/10/2016 17/10Hội phụng sự Xã Hội (USA) Giúp MS2309; Ms2310; Ms2311; Ms2315; Ms2317 (Mỗi h/c 2,000,000 đ); MS2312 (3,000,000 đ\") Ms2314; Ms2316 (Mỗi h/c \"1,000,000 đ\"15,000,000 Phùng Tiến Long (Nhà 10- Ngõ 272 - Đường Hữu Hưng - Đại Mỗ - Nam Từ Liêm -HN) Ủng hộ QNA1,000,000 Bạn đọc (HN) Giúp Ms2313 \"1,000,000 đ\"; Ms2312; 2,000,000 đ\"; Ms23111,000,000 đ\"4,000,000 Nguyễn Hoàng Vinh (Nha Trang - Khánh Hòa) Giúp Ms2289 (Nhận thư qua BĐ Lần 1 + Lần 2))120,00018/10Lương Minh Phúc (Tân Mỹ - Mỹ Đình -HN) Giup sMs2319110,000 Phạm Thị Diệu Hoa (C.H L.B Đức) Giúp Ms2312; Ms2307; Ms2311; Ms2304 (Mỗi h/c 500k)2,000,000 Trịnh Thị Mai (C.H L.B Đức) Giúp Ms2311; Ms2315 (Mỗi h/c 200k)400,000 Nguyễn Thị Thu Hà (Nhà liền kề 60 - Mỗ Lao - Hà Đông -HN) Giup sMs2317; Ms2314 (Mỗi h/c 1,000,000 đ)2,000,000 Đặng Quỳnh Hoa (Số 15/8/379 Đội Cấn -HN) Giúp MS23201,000,000 Nguyễn Văn Tường (Phường Ngọc Lâm - Q.Long Biên-HN) Giúp Ms2314500,000 Nguyễn Đăng Khoa (Hoàng Hoa Thám -HN) Giúp Ms2318150,00019/10C.ty CP truyền thông quảng cáo đa phương tiện SMART MEDIA (tầng 5 tòa nhà Intracom- số 82 Dịch Vọng Hậu - Cầu giấy -HN) Giúp MS232015,000,000 Tuấn Anh (Số 34 Quang Trung - Hoàn Kiếm -HN) Giúp Ms2319 \"200,000 đ\"; Ms2321 \"100,000 đ\"300,000 Anh Quân (Ngõ 29 - Thụy Khuê -HN) Giup sMS2321; Ms2302; Ms2320 (Mỗi Ms \"100,000 đ\"300,000 Quỳnh Ngọc (Khương Trung -HN) Giúp MS2320200,000 Bà Trần Thị Tý (Tân Kỳ - Nghệ An ) Giúp MS2320100,000 Gia đình bà Võ Thị Thương Lan (Số 15 - Ngõ 1132 Đường Láng -HN) Giúp Ms23203,000,000 Vũ Minh Sáng (Vĩnh Ngọc - Đông Anh -HN) Giúp Ms2320500,000 Nguyễn Đăng Vĩnh (Đống Đa -HN) Giúp Ms2319500,000 Lê Thị Trà My (Số nhà 105 khu tập thể 16B - Ngô Tất Tố - Ba Đình -HN) Giúp Ms2320300,000 Phan Thị Thu Hiền - Nguyễn Kim Cương (Khoa Sinh - Kỹ Thuật Nông Nghiệp- ĐHSP2 HN) Giúp Ms2318; Ms2295 (Mỗi h/c 200,000 đ); Ms2321; Ms2317; Ms2267; Ms2268; MS2270; Ms2271; Ms2280; Ms2274 (Mỗi h/c 100k)1,200,00020/06C.t.y CP Tư vấn và Kỹ thuật môi trường An Bình (Số 10 - ngõ 81 Mễ Trì Thượng - Mỹ Đình -HN) Giúp Ms23202,000,000 Cao thị Cẩm Tú (P1406 - A2 - Số 299 - Phố vọng -HN) Giúp Ms2320500,000 Nguyễn Hải Nam (Số nhà 52 - Ngõ 62 - Ngọc Hà - Ba Đình -HN) Giúp Ms23201,000,000 Nguyễn Hải Trường (Số nhà 52 - Ngõ 62 - Ngọc Hà -HN) Giúp Ms23201,000,000 Nguyễn Kim Phượng (Sóc Trăng ) Giúp Ms23201,250,000 Nguyễn Minh Hiếu (Số 24 Nguyễn Siêu -HN) Giúp Ms2322100,000 Hoàng Duy Anh (HN) Giúp MS23203,000,000 Hoàng Lê Tỷ Tỷ (Hà Đông -HN) Giúp Ms2320100,000 Bà Lê Thị Lân (Số 29C- Ngõ 6 - Đặng Văn Ngữ -HN) Giúp Ms23201,000,00021/10C.ty TNHH Thương Mại (số 286 Đường Chiến Thắng - Văn quán - Hà Đông -HN) giúp Ms2320 PT53 \"10,000,000 đ\"10,000,000 Đỗ Thị Vang (Tổ 7, Yên Hòa - Cầu Giấy -HN) Giúp Ms2320500,000 Nguyễn Văn Công (Số 116 Mai Anh Tuấn - Đống Đa -HN) Giup sMs2322; Ms2319; Ms2305; MS2306; Ms2294 (Mỗi h/c 2,000,000 đ)10,000,000 Nguyễn Đức Dũng (Cát Động - Thị Trấn Kim Bài - Thanh Oai - HN) giúp Ms23191,000,000 Nguyễn Sinh Công Giúp Ms2318 (Nhận thư qua BĐ)100,00022/10Nguyễn Doãn Đức (Số 22 Ngõ 133 An Xá - Ba Đình -HN) Giúp Ms2322500,000 Hoàng Lang -Kim Giang (Thanh Xuân -HN) giúp Ms2322500,000 Hoàng Lang -Kim Giang (Thanh Xuân -HN) giúp Ms2323500,000 Bạn đọc dân trí Giúp Ms2319; Ms2323 (Mỗi h/c 300k)600,000 Công ty TNHH General Motors Ms2320 PT54 \"30.010.000 đ\"30,010,000 Trần Thị Hồng Phượng (Thành công - Ba Đình -HN) Giúp Ms2295500,000 Bé Đặng Quang Dũng (HN) Giúp MS2320415,000 Bạn đọc ủng Trực tuyến\n\t\t\ttừ ngày 16 đến 22/10/2016 16/10/2016Tham gia ủng hộ: 2316, 2315, 2313, 2312, 2311\n\t\t\tMỗi hoàn cảnh 100,000 - Số tiền: 500.000 đ - Họ tên: Trần Bảo Khánh - Điện thoại: 0937660113500,00016/10/2016Tham gia ủng hộ: Mã số 2317: Bà Nguyễn Thị Mới, ngụ ấp Bờ Kinh 2, xã Mỹ Hòa, huyện Cầu Ngang, tỉnh Trà Vinh - Số tiền: 150.000 đ - Họ tên: andre nguyen - Điện thoại: 01212607269150,00017/10/2016Tham gia ủng hộ: Mã số 2318: Chị Nguyễn Thị Hòa (thôn Hữu Chấp, xã Hòa Long, TP. Bắc Ninh, tỉnh Bắc Ninh) - Số tiền: 200.000 đ - Họ tên: Hồ Khánh Vân - Điện thoại: 01692964139200,00017/10/2016Tham gia ủng hộ: ung ho ma so 2318 - Số tiền: 300.000 đ - Họ tên: Nam Mô A Di Đà Phật - Điện thoại: 0938937711300,00017/10/2016Tham gia ủng hộ: Mã số 2318: Chị Nguyễn Thị Hòa (thôn Hữu Chấp, xã Hòa Long, TP. Bắc Ninh, tỉnh Bắc Ninh) - Số tiền: 200.000 đ - Họ tên: Nguyễn Đỗ Tường Vân - Điện thoại: 0919060160200,00017/10/2016Tham gia ủng hộ: Ms 2318 - Số tiền: 200.000 đ - Họ tên: Dinh thi thu - Điện thoại: 01299009203200,00018/10/2016Tham gia ủng hộ: Mã số 2318: Chị Nguyễn Thị Hòa (thôn Hữu Chấp, xã Hòa Long, TP. Bắc Ninh, tỉnh Bắc Ninh)\n\n\t\t\tSố ĐT: 01635.489.393 (Số con gái chị Hòa, em Nguyễn Thị Thanh Nga) - Số tiền: 100.000 đ - Họ tên: NMB - Điện thoại: 0987465130100,00018/10/2016Tham gia ủng hộ: Ung ho MS : 2319 - Số tiền: 200.000 đ - Họ tên: nhien - Điện thoại: 0909418787200,00018/10/2016Tham gia ủng hộ: Mã số 2319: Anh Nguyễn Văn Hoàng, xóm Trần Phú, xã Hậu Thành, Yên Thành, Nghệ An. - Số tiền: 500.000 đ - Họ tên: Le Giang Hung - Điện thoại: 0914830309500,00018/10/2016Tham gia ủng hộ: 2319 bé Nguyen Thi Anh Đài - Số tiền: 500.000 đ - Họ tên: Tuyet Mai - Điện thoại: 0907514974500,00018/10/2016Tham gia ủng hộ: Mã số 2319: Anh Nguyễn Văn Hoàng, xóm Trần Phú, xã Hậu Thành, Yên Thành, Nghệ An.\n\n\t\t\tĐiện thoại: 0967.950.791- anh Hoàng; TK: 65010001243189 (Phan Thị Phượng). - Số tiền: 200.000 đ - Họ tên: Lê Thị Bắc - Điện thoại: 0912662083200,00018/10/2016Tham gia ủng hộ: Mã số 2319 Bé Nguyễn Thị Anh Đài, chúc bé mau lành bệnh. - Số tiền: 250.000 đ - Họ tên: Phan Tấn Phong - Điện thoại: 0904645694250,00018/10/2016Tham gia ủng hộ: 2319\n\t\t\tNAM MO A DI DA PHAT - Số tiền: 50.000 đ - Họ tên: b. cầm - Điện thoại: 093539886650,00018/10/2016Tham gia ủng hộ: ms 2319 - Số tiền: 100.000 đ - Họ tên: dũng - Điện thoại: 0983684828100,00018/10/2016Tham gia ủng hộ: Mã số 2319: Anh Nguyễn Văn Hoàng, xóm Trần Phú, xã Hậu Thành, Yên Thành, Nghệ An. - Số tiền: 200.000 đ - Họ tên: mai - Điện thoại: 0938035273200,00018/10/2016Tham gia ủng hộ: Mã số 2319: Anh Nguyễn Văn Hoàng, xóm Trần Phú, xã Hậu Thành, Yên Thành, Nghệ An. - Số tiền: 200.000 đ - Họ tên: SơRI - Điện thoại: 0918161112200,00018/10/2016Tham gia ủng hộ: Mã số 2319 - Số tiền: 50.000 đ - Họ tên: NDT - Điện thoại: 090324571650,00018/10/2016Tham gia ủng hộ: 1. Mã số 2319: Anh Nguyễn Văn Hoàng, xóm Trần Phú, xã Hậu Thành, Yên Thành, Nghệ An.\n\n\t\t\tĐiện thoại: 0967.950.791- anh Hoàng; TK: 65010001243189 (Phan Thị Phượng). - Số tiền: 400.000 đ - Họ tên: taichau` - Điện thoại: 000000400,00018/10/2016Tham gia ủng hộ: 2318, 2319 mỗi MS 50.000 - Số tiền: 100.000 đ - Họ tên: phong - Điện thoại: 0944448666100,00018/10/2016Tham gia ủng hộ: 2283; 2290; 2318; 2319 mỗi MS 100.000 - Số tiền: 400.000 đ - Họ tên: phuc - Điện thoại: 0913931746400,00018/10/2016Tham gia ủng hộ: Mã số 2320: Giúp đỡ đồng bào miền Trung bị lũ lụt - Số tiền: 500.000 đ - Họ tên: mai xuan truong - Điện thoại: 0905878904500,00018/10/2016Tham gia ủng hộ: 2320 - Số tiền: 500.000 đ - Họ tên: Trần Thuý lệ - Điện thoại: 0983372382500,00019/10/2016Tham gia ủng hộ: Mã số 2320: Giúp đỡ đồng bào miền Trung bị lũ lụt - Số tiền: 100.000 đ - Họ tên: NMB - Điện thoại: 0987465130100,00019/10/2016Tham gia ủng hộ: Mã số 2317: Bà Nguyễn Thị Mới, ngụ ấp Bờ Kinh 2, xã Mỹ Hòa, huyện Cầu Ngang, tỉnh Trà Vinh ; 200.000VND\n\n\t\t\tMã số 2318: Chị Nguyễn Thị Hòa (thôn Hữu Chấp, xã Hòa Long, TP. Bắc Ninh, tỉnh Bắc Ninh) : 200.000VND\n\t\t\t- Số tiền: 400.000 đ - Họ tên: nguyen thi tuong vi - Điện thoại: 0989462635400,00019/10/2016Tham gia ủng hộ: 2320 - Số tiền: 1.000.000 đ - Họ tên: Le Nguyen - Điện thoại: 04304665281,000,00019/10/2016Tham gia ủng hộ: MS 2231- ANH NGUYỄN ĐÌNH THAO - Số tiền: 200.000 đ - Họ tên: HOÀNG CHINH - Điện thoại: 0979101178200,00019/10/2016Tham gia ủng hộ: MS 2319- ANH NGUYỄN VĂN HOÀNG - Số tiền: 200.000 đ - Họ tên: HOÀNG CHINH - Điện thoại: 0979101178200,00019/10/2016Tham gia ủng hộ: MS 2318- CHỊ NGUYỄN THỊ HÒA - Số tiền: 200.000 đ - Họ tên: HOÀNG CHINH - Điện thoại: 0979101178200,00019/10/2016Tham gia ủng hộ: Mã số 2318, chị nguyễn thị hòa, bắc ninh - Số tiền: 100.000 đ - Họ tên: Trinh thi thu nga - Điện thoại: 0995926269100,00019/10/2016Tham gia ủng hộ: Mã số 2320 ,Mã số 2318, mỗi mã 50k - Số tiền: 100.000 đ - Họ tên: NGUYỄN KỲ THƯ - Điện thoại: 123100,00019/10/2016Tham gia ủng hộ: Mã số 2320, giúp đỡ đồng bào miền Trung lũ lụt - Số tiền: 500.000 đ - Họ tên: Nguyễn Thị Hồng Bích - Điện thoại: 0982863010500,00019/10/2016Tham gia ủng hộ: ủng hộ đồng bào miền trung - Số tiền: 100.000 đ - Họ tên: gấu sóc - Điện thoại: 0935398866100,00019/10/2016Tham gia ủng hộ: Mã số 2321: Anh Nguyễn Đình Thao, tổ dân phố 1, phường Đại Nài, thành phố Hà Tĩnh - Số tiền: 100.000 đ - Họ tên: duy vu - Điện thoại: 9836116553100,00019/10/2016Tham gia ủng hộ: Mã số 2319:\n\t\t\tỨa nước mắt với bé gái 4 tháng tuổi tứ chi co quắp vì không có tiền chữa trị - Số tiền: 250.000 đ - Họ tên: Linh Uyen va Duc Tri - Điện thoại: 0912423399250,00020/10/2016Tham gia ủng hộ: Mã số 2319;2320;2321;2322 ủng hộ mỗi mã số 100.000 đ - Số tiền: 400.000 đ - Họ tên: Hằng - Điện thoại: 0903777559400,00020/10/2016Tham gia ủng hộ: Mã số 2322:\n\t\t\tChị Nguyễn Thị Mạnh, Phú Đa, xã Hồng Khê, huyện Bình Giang, Hải Dương. - Số tiền: 200.000 đ - Họ tên: Phuong - Điện thoại: 0903686217200,00020/10/2016Tham gia ủng hộ: Mã số 2320 - Số tiền: 500.000 đ - Họ tên: Lam lu Chi - Điện thoại: 1111111111500,00020/10/2016Tham gia ủng hộ: 2322 - Số tiền: 200.000 đ - Họ tên: tannguyen - Điện thoại: 0979750710200,00020/10/2016Tham gia ủng hộ: 2330 - Số tiền: 200.000 đ - Họ tên: phong - Điện thoại: 0944448666200,00021/10/2016Tham gia ủng hộ: MS 2323 - Số tiền: 200.000 đ - Họ tên: Huỳnh Thị Thúy Vân (Đà Nẵng) - Điện thoại: 0983458059200,00021/10/2016Tham gia ủng hộ: Mã số 2320: Giúp đỡ đồng bào miền Trung bị lũ lụt - Số tiền: 1.000.000 đ - Họ tên: Steve & Delie - Điện thoại: 09031268681,000,00021/10/2016Tham gia ủng hộ: Mã số 2319: Anh Nguyễn Văn Hoàng, xóm Trần Phú, xã Hậu Thành, Yên Thành, Nghệ An.\n\n\t\t\tĐiện thoại: 0967.950.791- anh Hoàng - Số tiền: 500.000 đ - Họ tên: Steve & Delie - Điện thoại: 0903126868500,00021/10/2016Tham gia ủng hộ: Ủng hộ MS 2312, MS 2318, MS 2319, MS 2323 mỗi trường hợp 100k vnd. - Số tiền: 400.000 đ - Họ tên: Lê Minh Huy - Điện thoại: 0934612383400,00021/10/2016Tham gia ủng hộ: 2320 - Số tiền: 300.000 đ - Họ tên: Nga - Điện thoại: 0911242165300,00021/10/2016Tham gia ủng hộ: Mã số 2322: Chị Nguyễn Thị Mạnh (thôn Phú Đa, xã Hồng Khê, huyện Bình Giang, Hải Dương) - Số tiền: 150.000 đ - Họ tên: andre nguyen - Điện thoại: 01212607269150,00021/10/2016Tham gia ủng hộ: Mã số 2323 - Số tiền: 200.000 đ - Họ tên: DeislerX - Điện thoại: 0904000000200,00021/10/2016Tham gia ủng hộ: Mã số 2323:\n\n\t\t\tBố mẹ mất vì tai nạn giao thông, bé gái 5 tuổi bơ vơ nằm viện - Số tiền: 100.000 đ - Họ tên: Nguyễn Chân Lý - Điện thoại: 0908607643100,00021/10/2016Tham gia ủng hộ: 1. Mã số 2319: Anh Nguyễn Văn Hoàng, xóm Trần Phú, xã Hậu Thành, Yên Thành, Nghệ An. - Số tiền: 200.000 đ - Họ tên: Nguyễn Đỗ Tường Vân - Điện thoại: 0919060160200,00021/10/2016Tham gia ủng hộ: 1. Mã số 2319: Anh Nguyễn Văn Hoàng, xóm Trần Phú, xã Hậu Thành, Yên Thành, Nghệ An. - Số tiền: 500.000 đ - Họ tên: Bùi Thị Thu Hoàng - Điện thoại: 0913160222500,00021/10/2016Tham gia ủng hộ: 1. Mã số 2322: Chị Nguyễn Thị Mạnh (thôn Phú Đa, xã Hồng Khê, huyện Bình Giang, Hải Dương) - Số tiền: 500.000 đ - Họ tên: Bùi Thị Thu Hoàng - Điện thoại: 0913160222500,00021/10/2016Tham gia ủng hộ: tôi ủng hộ đồng bào miền Trung - Số tiền: 300.000 đ - Họ tên: Nguyễn Thị Như Quỳnh - Điện thoại: 0945412776300,00021/10/2016Tham gia ủng hộ: Ms2319: 200k, Ms2320: 300k - Số tiền: 500.000 đ - Họ tên: Dinh thi thu - Điện thoại: 01299009203500,00022/10/2016Tham gia ủng hộ: Mã số 2320: Giúp đỡ đồng bào miền Trung bị lũ lụt - Số tiền: 500.000 đ - Họ tên: Vương Sanh Khoài - Điện thoại: 0908495991500,000 Bạn đọc ủng hộ qua Vp Miền Nam\n\t\t\ttừ ngày 16 đến 22/10/2016 17/10Thịnh, Vượng giúp MS 2320 (đồng bào bị lũ lụt miền Trung)150,000 Gia đình Trần Tuấn Kiệt giúp MS 2318500,00018/10Hà Bentley giúp MS 2317, 2318200,000 Hưng giúp MS 2285, 2288, 2292, 2293, 2300, 2319600,000 Anh Tùng, PN, giúp MS 23201,200,00019/10Nghĩa Phan giúp MS 23182,240,000 Dương Quốc Trưởng giúp MS 2319, 23201,000,000 Anh chị Tạ Duy Trí, USA, giúp MS 23181,000,00020/10Lieu Doan giúp MS 23201,120,00021/10Trần Ngọc Lương giúp MS 2310500,000 Phụng Châu, Nguyễn Thụy Ngọc Mỵ, Tâm Hoài giúp MS 2313, 2314, 2311, 2305, 23152,500,000 Bạn đọc giúp MS 2312, 2319 (200.000/MS), 2320 (500.000)900,000 Bạn đọc ủng hộ qua Vp Đà Nẵng\n\t\t\ttừ ngày 16 đến 22/10/2016 19/10Teresa Le Vu (USA) giúp đỡ mã số 2291 (giúp đỡ 20 USD=445.100 VNĐ, quy đổi theo tỷ giá ngày 19/10/2016, 1USD=22.255VNĐ, tỷ giá dưới 50USD)445,10019/10Bạn đọc Nguyễn Tấn Ngọc (Đà Nẵng) giúp đỡ mã số 2320800,00019/10Đình Hoà (VPĐN) giúp đỡ mã số 2320500,00019/10Tôn Thất Đại Dương (VPĐN) giúp đỡ mã số 2320200,00019/10Đoàn Thị Khánh Hiền (VPĐN) giúp đỡ mã số 2320200,00019/10Lê Doãn Công (VPĐN) giúp đỡ mã số 2320200,00019/10Dương Hồng Vương (VPĐN) giúp đỡ mã số 2320400,00019/10Ngô Huy Đức (50 Bình Hoà 1, Cẩm Lệ, Đà Nẵng) giúp đỡ mã số 2321200,000 Nguyễn Văn Kiệt (Đà Nẵng) giúp đỡ 13 trường hợp: MS 2241, MS 2246, MS 2252, MS 2251, MS 2258, MS 2261, MS 2263, MS 2264, MS 2273, MS 2276, MS 2285, MS 2289, MS 2303 (mỗi trường hợp 200.000đ)2,600,000 Bạn đọc ủng hộ qua Vp Hà Tĩnh\n\t\t\ttừ ngày 16 đến 22/10/2016 10/10/2016Nguyễn Ngọc Quý, phường Tân Giang, TP Hà Tĩnh Giúp Mã số: 2311200,000 Nguyễn Văn Nguyên, xã Thạch Hạ, TP Hà Tĩnh Giúp các Mã số: 2320; 2321; 23234,000,000 Bạn đọc ủng hộ qua ngân hàng Vietcombanktừ ngày 16 đến 22/10/2016 16/10/2016NGUYEN NGOC BINH GIUP MS 231750,00016/10/2016NGUYEN DINH PHUC GIUP MS 2317200,00016/10/2016LE MINH TUAN GIUP MS 2317200,00016/10/2016HANH LAN GIUP MS 2317200,00016/10/2016NGO TUAN ANH GIUP MS 2320200,00016/10/2016TRAN HUU THACH GIUP MS 2317500,00016/10/2016NGUYEN QUANG LINH GIUP MS 227770,00016/10/2016LE DUC ANH GIUP QNA100,00016/10/2016DOAN TRUNG TIN GIUP MS 2315500,00016/10/2016NGUYEN HONG PHUONG GIUP MS 2317200,00016/10/2016HIEU NGHIA GIUP MS 231710,00016/10/2016PHAN THI MAI THANH GIUP QNA50,00016/10/2016NGUYEN TUAN GIUP MS 2316100,00017/10/2016KHUC ANH HUNG GIUP MS 2314500,00017/10/2016BAN DOC GIUP QNA200,00017/10/2016CHU THI THANH GIUP QNA100,00017/10/2016TRAN DONG KINH GIUP MS 231820,000,00017/10/2016BAN DOC GIUP QNA500,00017/10/2016NGUYEN DANG DUY GIUP MS 2313200,00017/10/2016NGUYEN DANG DUY GIUP MS 2305200,00017/10/2016TRAN MINH QUYNH DUNG GIUP MS 23145,000,00017/10/2016TRAN MINH QUYNH DUNG GIUP MS 23152,000,00017/10/2016NGUYEN THI PHUONG THAO GIUP MS 2315100,00017/10/2016HOANG THI THU XUAN, BUI MINH PHUONG GIUP MS 23181,000,00017/10/2016NGUYEN THI HOANG YEN GUP MS 2318100,00017/10/2016NGUYEN THI HOANG YEN GUP MS 2314100,00017/10/2016NGUYEN THI HOANG YEN GUP MS 2315100,00017/10/2016NGUYEN THI HOANG YEN GUP MS 2311100,00017/10/2016NGUYEN THI HUE GIUP MS 2286300,00017/10/2016NGUYEN BICH NGOC GIUP MS 2318500,00017/10/2016NGUYEN THI PHUONG THAO GIUP MS 2318100,00017/10/2016HOANG VIET PHUONG GIUP MS 231851,38917/10/2016PHAM XUAN LAM GIUP MS 2318300,00017/10/2016NGUYEN THI THU HIEN GIUP MS 2318500,00017/10/2016LUONG THI THU THUY GIUP MS 2318300,00017/10/2016NGUYEN VAN CHUNG GIUP MS 2306500,00017/10/2016NGO QUANG TIEN GIUP MS 2318100,00017/10/2016BAN DOC GIUP MS 2318200,00017/10/2016BAN DOC GIUP MS 2317200,00017/10/2016BAN DOC GIUP MS 2317100,00017/10/2016BAN DOC GIUP MS 2318250,00017/10/2016BAN DOC GIUP MS 2318500,00017/10/2016LE THI NGOC MAI GIUP MS 2318200,00017/10/2016NGUYEN NGOC BINH GIUP MS 231850,00017/10/2016DIEP HOANG HA GIUP MS 2318100,00017/10/2016NGUYEN MAI HIEN GIUP MS 2311100,00017/10/2016NGUYEN MAI HIEN GIUP MS 2307100,00017/10/2016NGUYEN MAI HIEN GIUP MS 2304100,00017/10/2016NGUYEN XUAN BACH GIUP QNA100,00017/10/2016VO THI LAN CHI GIUP MS 2301500,00017/10/2016DO MANH HUNG GIUP MS 2318200,00017/10/2016NGUYEN KHANH THU LINH GIUP MS 2318200,00017/10/2016BUI DANG TUAN GIUP MS 2318300,00017/10/2016HA TRUNG HIEU GIUP MS 2315500,00017/10/2016TRAN MINH HAI GIUP MS 2315100,00017/10/2016DOAN LAN PHUONG GIUP MS 2316100,00017/10/2016TRAN MINH HAI GIUP MS 2312100,00017/10/2016TRAN MINH HAI GIUP MS 2311100,00017/10/2016LE THI HUONG GIUP MS 2312100,00017/10/2016PHAM HONG QUAN GIUP MS 2317500,00017/10/2016TRAN THANH HAI GIUP MS 2318500,00017/10/2016HOANG THUY DUNG GUP MS 2315500,00017/10/2016NGO VAN TIN GIUP MS 2318300,00017/10/2016DO THI PHUONG GIUP MS 2222500,00017/10/2016PHAM THI MY HANH GIUP MS 2318200,00017/10/2016NGUYEN VU DUNG GIUP MS 2318500,00017/10/2016NGUYEN THI THANH HUONG GIUP MS 2318500,00017/10/2016BUI VIET NGA GIUP MS 2317300,00017/10/2016HO MINH TRI GIUP MS 2318100,00017/10/2016NGO QUY KHA GIUP MS 2312200,00017/10/2016NGUYEN DAC THANG GIUP MS 23181,000,00017/10/2016NGO QUY KHA GIUP MS 2305200,00017/10/2016NGO QUY KHA GIUP MS 2311200,00017/10/2016NGO QUY KHA GIUP MS 2269200,00017/10/2016LE THANH CONG GIUP MS 2316100,00017/10/2016NGUYEN THI TUYET PHUONG GIUP MS 2304200,00017/10/2016NGUYEN THI TUYET PHUONG GIUP MS 2308200,00017/10/2016NGUYEN THI TUYET PHUONG GIUP MS 2310200,00017/10/2016NGUYEN THI TUYET PHUONG GIUP MS 2312200,00017/10/2016NGUYEN THI TUYET PHUONG GIUP MS 2315200,00017/10/2016NGUYEN THI TUYET PHUONG GIUP MS 2318200,00017/10/2016LUONG DIEP NGUYEN, LUONG CAO MINH GIUP MS 2318300,00017/10/2016NGUYEN DAN CHU GIUP MS 2318500,00017/10/2016VU VAN AN GIUP MS 2318100,00017/10/2016LE HOANG TRUNG GIUP MS 2318100,00017/10/2016DINH THU TRANG GIUP QNA500,00017/10/2016NGO VIET TUAN GIUP MS 2318200,00017/10/2016VU XUAN CUONG GIUP MS 231820,00017/10/2016GD BE GAU MINH TRI VA 2 BEN NOI NGOAI GIUP MS 2318300,00017/10/2016CHU VAN CHUONG GIUP MS 23181,000,00017/10/2016HO THI HOA GIUP MS 2318200,00017/10/2016VU THI HA GIUP MS 2312200,00017/10/2016VU THI HA GIUP MS 2305200,00017/10/2016TRIEU MAI LAN GIUP MS 2317100,00017/10/2016NGUYEN DO ANH THU GIUP MS 2305200,00017/10/2016NGUYEN DO ANH THU GIUP MS 2315200,00017/10/2016NGUYEN DO ANH THU GIUP MS 2318200,00017/10/2016DANG THI DIEM MY GIUP MS 2318200,00017/10/2016BE NGUYEN THIEN TAM GIUP MS 2318200,00017/10/2016NGUYEN THI MINH XUAN GIUP MS 2318500,00017/10/2016LETHI DIEM HUONG GIUP MS 2318300,00017/10/2016NGUYEN CHI THANH GUP MS 2318100,00017/10/2016NGO CAM THANH GIUP MS 2318500,00017/10/2016NGUYEN HUNG CUONG GIUP MS 2318100,00017/10/2016HOANG TRUNG DINH GIUP MS 2318500,00017/10/2016NGUYEN THI NGOC MINH GIUP MS 2318200,00017/10/2016NGUYEN THI THIEP GIUP MS 2318200,00017/10/2016TRAN NGOC UYEN GIUP MS 2318300,00017/10/2016NGUYEN THANH HUNG GIUP MS 2305 DEN 2318 (BO MS 2308, 2311, 2312, 15,16)900,00017/10/2016NGUYEN HOANG YEN GIUP MS 2318200,00017/10/2016PHAM THANH HAI GIUP MS 2318300,00017/10/2016LE QUANG HOA GIUP MS 2318300,00017/10/2016DAO MINH KHUE GIUP MS 2301 DEN 2306.600,00017/10/2016DUONG THI PHUONG LAN GIUP MS 2291200,00017/10/2016DAO ANH KHOI GIUP MS 2307 DEN 2312.600,00017/10/2016VO VAN HUY GIUP MS 2318100,00017/10/2016PHAM TUAN THANH GIUP MS 2318500,00017/10/2016DANG HOANG AN GIUP MS 23181,000,00017/10/2016NGUYEN PHAT HUY GIUP MS 2318700,00017/10/2016NGUYEN NGOC THANG GIUP MS 2318300,00017/10/2016BUI THU THAI GIUP MS 2318200,00017/10/2016NGUYEN BA TUAN GIUP MS 23181,000,00017/10/2016GIANG THI THUY NINH GIUP MS 2305100,00017/10/2016GIANG THI THUY NINH GIUP MS 2300100,00017/10/2016NGUYEN THI MINH AI GIUP MS 2318200,00017/10/2016NGUYEN BUI LAM ANH GIUP QNA300,00017/10/2016PHAM DUC THANG GIUP MS 2317100,00017/10/2016PHAM DUC THANG GIUP MS 2318100,00017/10/2016NGUYEN GIA TAM NHA GIUP MS 2315300,00017/10/2016NGUYEN THUY HUONG GIUP MS 2320500,00017/10/2016TRAN THI THU TRANG GIUP MS 2312500,00017/10/2016NGUYEN GIA TAM NHA GIUP MS 2316300,00017/10/2016BUI LINH HUONG GUP MS 23201,000,00017/10/2016DO THUY NGA GIUP MS 2317300,00017/10/2016NGUYEN THI THANH HA GIUP MS 2305200,00017/10/2016VU NGOC HONG GIUP MS 2318300,00017/10/2016LE TRUONG THU HUONG GIUP MS 2318100,00017/10/2016TRINH THU NGOC GIUP MS 23181,000,00017/10/2016LE DUC ANH GIUP QNA100,00017/10/2016NGUYEN THI NGUYET ANH GIUP MS 2305100,00017/10/2016NGUYEN THI NGUYET ANH GIUP MS 2312100,00017/10/2016NGUYEN THI BICH THUY GIUP MS 2318200,00017/10/2016CHAU HOANG QUAN GIUP MS 2318100,00017/10/2016LA THI HONG TUOI GIUP MS 2315100,00017/10/2016PHAN THI THANH HUYEN GUP MS 231880,00017/10/2016TRAN THI MAO GIUP MS 2318300,00017/10/2016NGUYEN THI HUONG THUY GIUP MS 2318200,00017/10/2016DO NGUYEN NGOC THU GIUP MS 2315300,00017/10/2016NGUYEN XUAN DUC GIUP MS 2318200,00017/10/2016PHAN NGOC HUNG GIUP MS 2315 DEN 2318.400,00017/10/2016VU TIEN QUYET GIUP MS 2318500,00017/10/2016NGUYEN THI HUONG GIANG IGUP MS 2312300,00017/10/2016NGUYEN THI HUONG GIANG IGUP MS 2316300,00017/10/2016NGUYEN THI HUONG GIANG IGUP MS 2317300,00017/10/2016DO NGUYEN NGOC THU GIUP MS 2317300,00017/10/2016DO NGUYEN NGOC THU GIUP MS 2318300,00017/10/2016HIEU NGHIA GIUP MS 231810,00017/10/2016NGUYEN HONG PHUONG GIUP MS 2318200,00017/10/2016TRAN QUOC DAO GIUP MS 2318150,00017/10/2016TRUONG CONG THANH GIUP MS 23091,000,00017/10/2016TRUONG CONG THANH GIUP MS 23101,000,00017/10/2016TRUONG CONG THANH GIUP MS 23111,000,00017/10/2016TRUONG CONG THANH GIUP MS 23121,000,00017/10/2016DINH ANH TUAN GIUP MS 2315100,00017/10/2016PHAM VAN HIEU GIUP MS 2314400,00017/10/2016PHAM VAN HIEU GIUP MS 2316400,00017/10/2016PHAM VAN HIEU GIUP MS 2315400,00018/10/2016TRUONG NGOC LAN GIUP MS 2315100,00018/10/2016TRUONG NGOC LAN GIUP MS 2307100,00018/10/2016TRUONG NGOC LAN GIUP MS 2305100,00018/10/2016TRUONG NGOC LAN GIUP MS 2301100,00018/10/2016TRUONG NGOC LAN GIUP MS 2300100,00018/10/2016TRUONG NGOC LAN GIUP MS 2299100,00018/10/2016TRUONG NGOC LAN GIUP MS 2297100,00018/10/2016TRUONG NGOC LAN GIUP MS 2295100,00018/10/2016TRUONG NGOC LAN GIUP MS 2294100,00018/10/2016CHU THI NHUNG GIUP MS 2319200,00018/10/2016CAO HOANG PHUONG THAO GIUP MS 2319200,00018/10/2016CONG TY TNHH TM VU HAI GIUP MS 2312 DEN 2319.2,400,00018/10/2016TRAN THI THAO GIUP MS 2316300,00018/10/2016NGUYEN THU HUONG GIUP MS 2319200,00018/10/2016TRAN THI THANH NGA GIUP MS 2319200,00018/10/2016NGUYEN THI BICH VAN GIUP MS 2316150,00018/10/2016TA THI PHUONG THAO GIUP MS 2319200,00018/10/2016TRAN DINH LONG GIUP MS 2319400,00018/10/2016BAN DOC GIUP QNA2,000,00018/10/2016PHAM HOANG HA GIUP MS 2318200,00018/10/2016DAO TRONG VUONG GIUP MS 2311500,00018/10/2016NGUYEN THI PHUONG GIUP MS 2319300,00018/10/2016DAO THI THANH THUY GIUP MS 2319300,00018/10/2016NGO ANH DUONG GIUP MS 2319100,00018/10/2016LE THI HA LINH GIUP MS 2319200,00018/10/2016DINH THI KHOAN GIUP MS 2319500,00018/10/2016HA QUOC THINH GIUP MS 2319100,00018/10/2016PHAM THI PHUONG GIUP MS 2319200,00018/10/2016NGUYEN TIN GIUP MS 23191,000,00018/10/2016NGUYEN THI GIANG HUONG GIUP MS 2319200,00018/10/2016BUI THI THUY LINH IGUP MS 2319100,00018/10/2016DINH THI NINH GIUP MS 2319250,00018/10/2016DINH THI NINH GIUP MS 2295250,00018/10/2016LE THI CAM HUYEN GIUP MS 2319100,00018/10/2016CTY CP O TO ASC GIUP MS 2319500,00018/10/2016CTY CP O TO ASC GIUP MS 2318500,00018/10/2016CTY CP O TO ASC GIUP MS 23171,000,00018/10/2016CTY CP O TO ASC GIUP MS 2316500,00018/10/2016BAN DOC IGUP MS 2318200,00018/10/2016BAN DOC IGUP MS 2318500,00018/10/2016BAN DOC IGUP MS 23181,000,00018/10/2016BAN DOC IGUP MS 231950,00018/10/2016BAN DOC IGUP MS 2319100,00018/10/2016BAN DOC IGUP MS 2319300,00018/10/2016BAN DOC IGUP MS 2319400,00018/10/2016MINH TUNG GIUP MS 231950,00018/10/2016BAN DOC GIUP MS 2319100,00018/10/2016BAN DOC GIUP MS 2319200,00018/10/2016BAN DOC GIUP MS 2319100,00018/10/2016BAN DOC GIUP MS 2320400,00018/10/2016BAN DOC GIUP MS 2299100,00018/10/2016BAN DOC GIUP MS 2300100,00018/10/2016BAN DOC GIUP MS 2301100,00018/10/2016BAN DOC GIUP MS 2304100,00018/10/2016BAN DOC GIUP MS 2306100,00018/10/2016BAN DOC GIUP MS 2311100,00018/10/2016BAN DOC GIUP MS 2312100,00018/10/2016BAN DOC GIUP MS 2313100,00018/10/2016BAN DOC GIUP MS 2318100,00018/10/2016BAN DOC GIUP MS 2319100,00018/10/2016BAN DOC GIUP MS 2320200,00018/10/2016LE DUC LAP GIUP MS 232050,00018/10/2016NGUYEN DUY NAM GIUP MS 2320200,00018/10/2016NGUYEN NGOC BINH GIUP MS 231950,00018/10/2016CHU THI NGUYET GIUP MS 231950,00018/10/2016NGUYEN THI THANH LOAN GIUP MS 2319100,00018/10/2016NGUYEN MINH HOA IGUP MS 2319500,00018/10/2016TRAN GIANG TUAN GIUP MS 2319200,00018/10/2016LUONG VAN NHAN GIUP MS 2319500,00018/10/2016NGUYEN THI HONG HANH GIUP MS 2319500,00018/10/2016NGUYEN THI HUE GIUP MS 2319500,00018/10/2016HUYNH CHAN TRUNG GIUP MS 2319100,00018/10/2016NGUYEN THI THU HANG GIUP MS 2319300,00018/10/2016SY SAU YEN GIUP MS 2318200,00018/10/2016NGUYEN MANH HA GIUP MS 2319150,00018/10/2016HOANG VAN CHUNG GIUP MS 2309200,00018/10/2016CONG TY TNHH HUY THANH GIUP MS 232010,000,00018/10/2016LE THI DIEU GIUP MS 2319100,00018/10/2016HONG CAT ANH GIUP MS 2319300,00018/10/2016MA VU HIEU LE GIUP MS 2318500,00018/10/2016LOC CA MUI GIUP MS 2319300,00018/10/2016GD BE VO PHAN MINH THU GIUP MS 2319150,00018/10/2016DO THANH BINH GIUP MS 2319200,00018/10/2016NGUYEN THANH MAI GUP MS 2319100,00018/10/2016TRINH TH THU THAO GIUP MS 2319200,00018/10/2016TRAN THI THUY GIUP MS 1433200,00018/10/2016NGUYEN THI THU HIEN GIUP MS 2319200,00018/10/2016HOANG VN DUNG GIUP MS 2319150,00018/10/2016HUYNH THI LAN HUONG GIUP MS 2319500,00018/10/2016NGUYEN HUU KHANH GUP MS 2319200,00018/10/2016KIEU THI HONG NHUNG GIUP MS 2319200,00018/10/2016NGUYEN THI MY HANH GIUP MS 2319200,00018/10/2016NGUYEN THI MINH TAM GIUP MS 2319300,00018/10/2016LUONG MAI GIUP MS 2313120,00018/10/2016LE THI DUNG GIUP MS 2319150,00018/10/2016MAI HAI YEN GIUP MS 2319100,00018/10/2016NGUYEN THU TRANG GIUP MS 2319100,00018/10/2016HA VAN THUAN GIUP MS 2319200,00018/10/2016TRAN THI NGOC ANH, CHAU THANH LIEM, MAN THU NHAT NAM GIUP MS 2309100,00018/10/2016TRAN THI NGOC ANH, CHAU THANH LIEM, MAN THU NHAT NAM GIUP MS 2310100,00018/10/2016TRAN THI NGOC ANH, CHAU THANH LIEM, MAN THU NHAT NAM GIUP MS 2313100,00018/10/2016TRAN THI NGOC ANH, CHAU THANH LIEM, MAN THU NHAT NAM GIUP MS 2318100,00018/10/2016TRAN THI NGOC ANH, CHAU THANH LIEM, MAN THU NHAT NAM GIUP MS 2319100,00018/10/2016PHUNG XUAN CUONG, DUC LONG GIUP MS 2319300,00018/10/2016NGUYEN THI NHUNG GIUP MS 2320100,00018/10/2016LE HONG PHUC IGUP MS 23202,000,00018/10/2016LE DIEP LAI GIUP MS 2320300,00018/10/2016NGUYEN HONG NGOC GIUP MS 2320300,00018/10/2016TRAN THI NGA GIUP MS 2319100,00018/10/2016VO THI UT GIUP MS 2317150,00018/10/2016VO THI UT GIUP MS 2318100,00018/10/2016VO THI UT GIUP MS 2319100,00018/10/2016DAO HAI HAU GIUP MS 23205,000,00018/10/2016VO THI UT GIUP MS 2320100,00018/10/2016NGUYEN MINH HOANG GIUP MS 2320200,00018/10/2016TRAN THI THU HIEN IGUP MS 23086,400,00018/10/2016VU VAN HUNG GIUP MS 2320200,00018/10/2016NGUYEN MANH HA GIUP MS 23201,000,00018/10/2016VU VAN DUNG GIUP MS 2318300,00018/10/2016VU VAN DUNG GIUP MS 2319300,00018/10/2016NGUYEN TRUONG GIANG IGUP MS 2319200,00018/10/2016NGUYEN THAI GIANG GIUP MS 2320200,00018/10/2016NGUYEN HUY BINH IGUP MS 2320500,00018/10/2016NGUYEN THI THIEP GIUP MS 2319100,00018/10/2016TRAN THI MAI GIUP MS 2319200,00018/10/2016VU THI QUYEN GUP MS 2319200,00018/10/2016HOANG DANG QUANG GIUP MS 2319200,00018/10/2016NGUYEN THI OANH GIUP MS 2319150,00018/10/2016DINH XUAN LOI GIUP MS 2319200,00018/10/2016DINH XUAN LOI GIUP MS 2306200,00018/10/2016DINH XUAN LOI GIUP MS 2281200,00018/10/2016DINH XUAN LOI GIUP MS 2294200,00018/10/2016DINH XUAN LOI GIUP MS 2311200,00018/10/2016DUONG DINH TU GIUP MS 2319200,00018/10/2016BUI THI TRA MY GIUP MS 23191,000,00018/10/2016LE TUNG QUOC GIUP MS 2319500,00018/10/2016NGUYEN THI DUNG GIUP MS 2319200,00018/10/2016NGUYEN HONG VY GIUP MS 2319500,00018/10/2016LE ANH VINH GIUP MS 2319100,00018/10/2016TA VAN THANG GIUP MS 2319200,00018/10/2016DINH THANH TUAN GIUP MS 2319100,00018/10/2016THAI HUY NHUNG GIUP MS 2319300,00018/10/2016NGUYEN DINH CONG GIUP MS 2319200,00018/10/2016PHAM MANH THANG GIUP MS 2317100,00018/10/2016PHAM MANH THANG GIUP MS 2318100,00018/10/2016PHAM MANH THANG GIUP MS 2319100,00018/10/2016VU THI HIEN GIUP MS 2315100,00018/10/2016VU THI HIEN GIUP MS 2317100,00018/10/2016VU THI HIEN GIUP MS 2319100,00018/10/2016NGUYEN THI LAN ANH GIUP MS 2319600,00018/10/2016VO THI HA XUYEN GIUP MS 2319300,00018/10/2016DAO THI THU HUONG GIUP MS 2319100,00018/10/2016NGUYEN THI THUY NGA GIUP MS 231950,00018/10/2016NGUYEN HOANG DUNG GIUP MS 2319100,00018/10/2016VU THI PHUONG LINH GIUP MS 2319300,00018/10/2016NGUYEN THI THUY GIUP MS 2319150,00018/10/2016PHAM BICH LIEN GIUP MS 2319200,00018/10/2016VU HOANG QUYEN, BUI THE KY GIUP MS 2319300,00018/10/2016NGUYEN THI DIEM HANH GIUP MS 2319200,00018/10/2016NGO THI HOA GIUP MS 2319100,00018/10/2016VU THI MAI GIUP MS 2319100,00018/10/2016LA BA QUYNH GIUP MS 2319500,00018/10/2016DO THI PHUONG UYEN GIUP MS 2319200,00018/10/2016LE VAN LAM GIUP MS 2319500,00018/10/2016LE VAN LAM GIUP MS 2318500,00018/10/2016LE VAN LAM GIUP MS 2313500,00018/10/2016LE VAN LAM GIUP MS 2312500,00018/10/2016LE VAN LAM GIUP MS 2309500,00018/10/2016LE VAN LAM GIUP MS 2308500,00018/10/2016LE VAN LAM GIUP MS 2307500,00018/10/2016LE VAN LAM GIUP MS 2306500,00018/10/2016LE VAN LAM GIUP MS 2300500,00018/10/2016LE VAN LAM GIUP MS 2297500,00018/10/2016LE VAN LAM GIUP MS 2292500,00018/10/2016LE VAN LAM GIUP MS 2283500,00018/10/2016LE VAN LAM GIUP MS 2250500,00018/10/2016LE VAN LAM GIUP MS 2205500,00018/10/2016NGUYEN THUC ANH GIUP MS 2319500,00018/10/2016NGUYEN VAN LAN GIUP MS 2319200,00018/10/2016TRAN MANH GIUP MS 2319500,00018/10/2016AN NGOC TUAN GIUP MS 23191,000,00018/10/2016NGUYEN TRONG TRINH GIUP MS 2319100,00018/10/2016NGUYEN BA TUAN GIUP MS 2319500,00018/10/2016THAI THI HUYEN TRANG GIUP MS 2319200,00018/10/2016DINH THE MINH GIUP MS 2319200,00018/10/2016NGUYEN MINH HANG GIUP MS 228850,00018/10/2016NGUYEN MINH HANG GIUP MS 229250,00018/10/2016NGUYEN MINH HANG GIUP MS 229950,00018/10/2016NGUYEN MINH HANG GIUP MS 230050,00018/10/2016NGUYEN MINH HANG GIUP MS 230550,00018/10/2016NGUYEN MINH HANG GIUP MS 231950,00018/10/2016NGUYEN THI HONG MINH GIUP MS 2319200,00018/10/2016NGUYEN CANH TOAN GIUP MS 2319200,00018/10/2016NGUYEN THI HIEN GIUP MS 2319200,00018/10/2016NGUYEN THI THU NGOC GIUP MS 2319200,00018/10/2016PHAM THI NGUYET GIUP MS 2319300,00018/10/2016HOANG MANH TUAN GIUP MS 2319300,00018/10/2016TRAN THI HONG HANH GIUP MS 2319100,00018/10/2016LE THI VIET HA GIUP MS 2319300,00018/10/2016HA VAN TU GIUP MS 2319100,00018/10/2016VU THI MINH HANG GIUP MS 2319200,00018/10/2016TON NU PHUONG THANH GIUP MS 2319300,00018/10/2016HOANG THE CUONG GIUP MS 231950,00018/10/2016NGUYEN CANH TOAN GIUP MS 2319300,00018/10/2016TRAN MINH CHAT GIUP MS 2319200,00018/10/2016BUI PHUONG ANH GIUP MS 2312300,00018/10/2016BUI PHUONG ANH GIUP MS 2316300,00018/10/2016BUI PHUONG ANH GIUP MS 2317300,00018/10/2016BUI PHUONG ANH GIUP MS 2318300,00018/10/2016HOANG THI THU HA GIUP MS 2318200,00018/10/2016PHAM BINH PHUONG THAO GUP MS 2317200,00018/10/2016NGUYEN DUY HOAI AN GIUP MS 2319200,00018/10/2016PHAM QUOC PHI LONG GIUP MS 2319200,00018/10/2016NGUYEN THANH BINH GIUP MS 2319100,00018/10/2016LE QUANG HOA GIUP MS 2319300,00018/10/2016NGUYEN THI HOANG HAU GIUP MS 2319200,00018/10/2016VO CHONG MINH PHUONG GIUP MS 2313100,00018/10/2016VO CHONG MINH PHUONG GIUP MS 2318300,00018/10/2016VO CHONG MINH PHUONG GIUP MS 2312300,00018/10/2016NGUYEN MINH HOANG GIUP MS 2311200,00018/10/2016NGUYEN MINH HOANG GIUP MS 2318200,00018/10/2016NGUYEN THI THANH THUY GIUP MS 231950,00018/10/2016VU THI HANG GIUP MS 2319200,00018/10/2016DINH MINH TUAN GIUP MS 2319500,00018/10/2016LE GIA TUE GIUP MS 2305200,00018/10/2016NGUYEN HUU AN GIUP MS 2317100,00018/10/2016NGUYEN HUU AN GIUP MS 2318100,00018/10/2016LE GIA TUE GIUP MS 2318100,00018/10/2016TRAN THI NGOC THANH GIUP MS 2319500,00018/10/2016NGUYEN QUANG HUY GUP MS 2319300,00018/10/2016NGUYEN HUU AN GIUP MS 2319150,00018/10/2016TONG VAN DUNG GIUP MS 231930,00018/10/2016LE GIA HAN GIUP MS 2319100,00018/10/2016HOANG VIET ANH GIUP MS 2319300,00018/10/2016NGUYEN THANH THIEN HUONG GIUP MS 2319200,00018/10/2016PHAM KIM THOA GIUP MS 2319100,00018/10/2016HUYNH THI KIM CHI GIUP MS 2319500,00018/10/2016TRAN THI PHUONG THAO GIUP MS 2319100,00018/10/2016NGUYEN THI NHU QUYNH GIUP MS 2319200,00018/10/2016TU THANH LAN GIUP MS 2318200,00018/10/2016LE NGOC LAN GIUP MS 2319300,00018/10/2016TU THANH LAN GIUP MS 2317200,00018/10/2016DINH THI CONG NUONG GIUP MS 2319300,00018/10/2016MAI TRA NY GIUP MS 2319100,00018/10/2016NGUYEN HUNG CUONG GIUP MS 2319100,00018/10/2016LE THI THANH HOAI GIUP MS 2301200,00018/10/2016NGUYEN THANH HIEU GIUP MS 2319100,00018/10/2016LE THI THANH HOAI GIUP MS 231950,00018/10/2016TRIEU VAN NGHI GIUP MS 2319300,00018/10/2016BUI DANG KHOA GIUP MS 2319500,00018/10/2016HIEU NGHIA GIUP MS 231910,00018/10/2016TRAN HOAI NAM GIUP MS 2319300,00018/10/2016DOAN THANH THUY GIUP MS 2319100,00018/10/2016NGUYEN THI THU THUY GIUP MS 2319200,00018/10/2016LE THANH PHONG GIUP MS 2319100,00018/10/2016LUU VAN QUY GIUP MS 2319100,00018/10/2016PHAM DUC ANH GIUP MS 2319100,00018/10/2016TRAN DUY KHANG GIUP MS 2300300,00018/10/2016NGUYEN THI HOAI THUONG GIUP MS 2318200,00018/10/2016TRAN DUY KHANG IGUP MS 2293350,00018/10/2016DO THI HAI TRANG GIUP MS 2319200,00018/10/2016NGUYEN THI THANH HUYEN GIUP MS 2319300,00018/10/2016DO THUY NGA GIUP MS 2319500,00018/10/2016NGUYEN HONG PHUONG GIUP MS 2319200,00018/10/2016VO CHIEN THANG GUIP MS 2319200,00018/10/2016LE THI HUYEN TRANG GIUP MS 23122300,00018/10/2016NGUYEN TRUONG GIANG GIUP MS 2318200,00018/10/2016PHAM TUAN DUONG GIUP MS 2318300,00018/10/2016LE XUAN HUYNH NGA GIUP MS 2318200,00018/10/2016LE THANH PHONG GIUP MS 2316100,00018/10/2016DOAN NHAT DUONG GIUP MS 2306200,00018/10/2016LE THANH PHONG GIUP MS 2317300,00018/10/2016DOAN NHAT DUONG GIUP MS 2310200,00018/10/2016LE THANH PHONG GIUP MS 2318100,00018/10/2016DOAN NHAT DUONG GIUP MS 2311200,00018/10/2016DOAN NHAT DUONG GIUP MS 2313200,00018/10/2016DOAN NHAT DUONG GIUP MS 2318200,00018/10/2016NGUYEN NAM HAI GIUP MS 231850,00018/10/2016NGUYEN SY HUNG GIUP MS 2318200,00018/10/2016NGO THI THU THANH GIUP MS 2318100,00018/10/2016NGUYEN SY HUNG GIUP MS 2290100,00018/10/2016NGUYEN SY HUNG GIUP MS 2289100,00018/10/2016NGUYEN SY HUNG GIUP MS 2293100,00018/10/2016NGUYEN SY HUNG GIUP MS 2294100,00018/10/2016NGUYEN SY HUNG GIUP MS 2301100,00018/10/2016NGUYEN SY HUNG GIUP MS 2303100,00018/10/2016NGUYEN SY HUNG GIUP MS 2307100,00018/10/2016NGUYEN SY HUNG GIUP MS 2311100,00018/10/2016VU HOANG LUONG GIUP QNA200,00019/10/2016PHAM THI HONG NHUNG GIUP MS 2320200,00019/10/2016NGUYEN QUANG GIAP GIUP MS 2319100,00019/10/2016NGUYEN QUANG GIAP GIUP MS 232150,00019/10/2016DINH THU HUONG GUP MS 23201,000,00019/10/2016TRAN THI LAN PHUONG GIUP MS 2319300,00019/10/2016VU THANH LAM GIUP MS 2320200,00019/10/2016HO DUY QUOC GIUP MS 2321100,00019/10/2016NGO XUAN HONG GIUP MS 23183,000,00019/10/2016PHAM THE HOA GIUP MS 2319300,00019/10/2016NGUYEN ANH DUNG GUP MS 2320200,00019/10/2016DO BAO ANH GIUP MS 23201,000,00019/10/2016TRAN HUU TRUYEN GIUP MS 23201,000,00019/10/2016VO NGUYEN HIEN GIUP MS 2319500,00019/10/2016DAO THI HANH GIUP MS 2295200,00019/10/2016DAO THI HANH GIUP MS 2306200,00019/10/2016DAO THI HANH GIUP MS 2308200,00019/10/2016DAO THI HANH GIUP MS 2311200,00019/10/2016DAO THI HANH GIUP MS 2321200,00019/10/2016TRAN NHU DUC HAU GIUP MS 2320500,00019/10/2016NGUYEN THI NGA GIUP MS 2321100,00019/10/2016HO QUOC TRI GIUP MS 2320200,00019/10/2016HO THI MUI GIUP MS 23201,300,00019/10/2016NGUYEN THI NGOC ANH GIUP MS 2319, 2318, 2317150,00019/10/2016TRAN THAI NGUYEN GIUP MS 2320100,00019/10/2016NGUYEN HONG THUY DUNG GIUP MS 2320300,00019/10/2016BAN DOC GIUP QNA200,00019/10/2016NGO VAN BO GIUP MS 2320200,00019/10/2016DO DUC HIEU GIUP MS 2318300,00019/10/2016TRAN MINH HUYEN GIUP MS 2319100,00019/10/2016TRUONG MY MY GIUP MS 2319300,00019/10/2016BAN DOC GIUP MS 23051,000,00019/10/2016NHU THANH HANG GIUP MS 2321500,00019/10/2016BAN DOC GIUP QNA400,00019/10/2016BAN DOC GIUP MS 23191,000,00019/10/2016BAN DOC GIUP MS 2320500,00019/10/2016BAN DOC GIUP MS 23205,825,00019/10/2016BAN DOC GIUP MS 2319300,00019/10/2016BAN DOC GIUP MS 23202,000,00019/10/2016BAN DOC GIUP MS 2319200,00019/10/2016BAN DOC GIUP MS 2319250,00019/10/2016BAN DOC GIUP MS 2319300,00019/10/2016NGUYEN VAN TIEP GUP MS 2319500,00019/10/2016BAN DOC GIUP MS 2319100,00019/10/2016BAN DOC GIUP MS 2321100,00019/10/2016NGUYEN HA QUYNH HUONG GIUP MS 2320500,00019/10/2016TRAN DUC DUNG GIUP MS 2320500,00019/10/2016TRAN THI HAO GIUP MS 2321100,00019/10/2016NGUYEN NGOC BINH GIUP MS 232150,00019/10/2016NGUYEN QUANG GIAP GIUP MS 2318100,00019/10/2016NGUYEN QUANG GIAP GIUP MS 231750,00019/10/2016NGUYEN THI KHUE GIUP MS 2320100,00019/10/2016HO THI THUC GIUP MS 232010,000,00019/10/2016BAN DOC GIUP QNA100,00019/10/2016DO VAN LIEN GIUP MS 23201,000,00019/10/2016AU THI THANH BINH GIUP MS 23201,000,00019/10/2016NGUYEN MINH TRI GIUP MS 23205,000,00019/10/2016NGUYEN THI OANH GIUP MS 2320500,00019/10/2016NGO THI NGOC ANH GIUP MS 23142,000,00019/10/2016CTY TNHH DTXD VÀ DVTM TRUONG PHU GUP MS 23202,000,00019/10/2016NGO SY HOANG, NGUYEN VAN MINH GIUP MS 2319200,00019/10/2016LE NGOC HUNG GIUP MS 23205,000,00019/10/2016NGUYEN PHUONG NGOC GIUP MS 2319500,00019/10/2016TANG THI THUY DUYEN GIUP MS 2320600,00019/10/2016TANG THI THUY DUYEN GIUP MS 2314200,00019/10/2016TANG THI THUY DUYEN GIUP MS 2318200,00019/10/2016PHAM THI THUY GIUP MS 2320300,00019/10/2016LE THI YEN TRUC GIUP MS 23201,000,00019/10/2016NGUYEN PHUOC THAO HOA GIUP MS 2319200,00019/10/2016PHAM ANH THU GIUP MS 2310300,00019/10/2016NGUYEN THANH TUNG GIUP MS 2317200,00019/10/2016NGUYEN THANH TUNG GIUP MS 2318200,00019/10/2016NGUYEN THANH TUNG GIUP MS 2319200,00019/10/2016NGUYEN THANH TUNG GIUP MS 2320200,00019/10/2016PHAM ANH THU GIUP MS 2310300,00019/10/2016TRIEU PHUNG HA GIUP MS 23201,000,00019/10/2016NGO THI NGOC GIUP MS 2319100,00019/10/2016NGO THI NGOC GIUP MS 2313100,00019/10/2016DO THI NGOC GUP MS 2320200,00019/10/2016TRAN QUANG TRI GIUP MS 2320500,00019/10/2016NGUYEN HOANG TRUNG HIEU THAO GIUP MS 2316100,00019/10/2016NGUYEN HOANG TRUNG HIEU THAO GIUP MS 2317100,00019/10/2016NGUYEN HOANG TRUNG HIEU THAO GIUP MS 2318100,00019/10/2016NGUYEN HOANG TRUNG HIEU THAO GIUP MS 2319100,00019/10/2016NGUYEN HOANG TRUNG HIEU THAO GIUP MS 2320100,00019/10/2016HUYNH THI THU HOA GIUP MS 2319300,00019/10/2016PHAM THI MY HANH GIUP MS 2320300,00019/10/2016DO DANH KHOA GIUP MS 2319100,00019/10/2016NGUYEN THANH QUE IGUP MS 2319500,00019/10/2016NGUYEN THU HA GIUP MS 2319200,00019/10/2016NGUYEN THI VAN ANH GUP QNA1,000,00019/10/2016DANG THI THU TRANG GIUP MS 2320200,00019/10/2016DANG THI THU TRANG GIUP MS 2319200,00019/10/2016LUONG THI NGOC HUYEN GIUP MS 2319500,00019/10/2016DANG YEN NGOC GIUP MS 2319300,00019/10/2016DANG DINH QUY GIUP MS 2320500,00019/10/2016NGUYEN THANH TRUNG GIUP MS 2320300,00019/10/2016ONG BA SU TAN GIUP MS 23205,000,00019/10/2016LE SY VAN GIUP MS 2321150,00019/10/2016NGUYEN VAN CHINH GIUP MS 2320500,00019/10/2016TRAN DUC MINH CHAU GIUP MS 2321100,00019/10/2016DO THI THU HOAI GIUP MS 23201,000,00019/10/2016NGUYEN THI THU HOA GIUP MS 2319200,00019/10/2016DAM TUYET VY GIUP MS 2320500,00019/10/2016NGUYEN TAI LONG GIUP MS 2319500,00019/10/2016HO ATAM GIUP MS 2320500,00019/10/2016NGUYEN TAI LONG IGUP MS 23201,000,00019/10/2016TRAN HOANG ANH GIUP MS 2318100,00019/10/2016TRAN HOANG ANH GIUP MS 2319200,00019/10/2016VU QUOC HOANG GIUP MS 23191,000,00019/10/2016TRAN HOANG ANH GIUP MS 2320100,00019/10/2016DO MINH QUAN GIUP MS 2320500,00019/10/2016NGUYEN ANH TUAN GIUP MS 2321150,00019/10/2016NGUYEN THI CUONG GIUP MS 2321500,00019/10/2016MAI THI NGUYET THANH GIUP MS 2320200,00019/10/2016DO MINH TUAN GIUP MS 2320100,00019/10/2016MAI THI NGUYET THANH GIUP MS 2321100,00019/10/2016LE THI BICH THANH GIUP MS 2319200,00019/10/2016NGUYEN THI THUY QUYNH GIUP MS 2321500,00019/10/2016LE HOANG SON GIUP MS 2320500,00019/10/2016NGUYEN THI THUY QUYNH GIUP MS 2319500,00019/10/2016TRAN THI LAN TRANG GIUP MS 2321100,00019/10/2016TRAN THI LAN TRANG GIUP MS 2319150,00019/10/2016NGUYEN THI HUONG GIUP MS 2320900,00019/10/2016VU THI KIM ANH GIUP MS 2319300,00019/10/2016NGUYEN THI THU HA GIUP MS 2321300,00019/10/2016NGUYEN NGOC LINH GIUP MS 2321200,00019/10/2016NGO HONG DUONG GIUP MS 2320500,00019/10/2016HO NGUYEN DUY GIUP MS 2320300,00019/10/2016NGUYEN THU HIEN GIUP MS 2319200,00019/10/2016NGUYEN NGOC THAO HIEN GIUP MS 2319500,00019/10/2016NGUYEN DUY LAM GIUP MS 2320500,00019/10/2016VO THI THANH THU GIUP MS 2320300,00019/10/2016DO KHANH LINH GIUP MS 2320500,00019/10/2016VU VIET HUNG GIUP MS 2320200,00019/10/2016VU THI THU HONG GIUP MS 2319100,00019/10/2016BUI HAI HA GIUP MS 2320500,00019/10/2016TRINH THU HA GIUP MS 2320100,00019/10/2016BUI HAI HA GIUP MS 2321500,00019/10/2016TA QUANG MINH TRI GIUP MS 23201,000,00019/10/2016NGUYEN ANH HAO GIUP MS 2320100,00019/10/2016PHAM NGOC SANG GIUP MS 2319400,00019/10/2016PHAM NGOC SANG GIUP MS 2321300,00019/10/2016NGUYEN THI PHUONG ANH GIUP MS 2320200,00019/10/2016HUYNH THI PHUONG LIEN GIUP MS 2319200,00019/10/2016NGO THI MINH TRANG GIUP MS 2321200,00019/10/2016LE THI SONG NGA GIUP MS 23201,000,00019/10/2016BUI ANH LY GIUP MS 23201,000,00019/10/2016VC NGUYEN VAN LINH, HOANG THI THANH HUYEN GIUP MS 2320500,00019/10/2016DUONG THI UYEN GIUP MS 2320200,00019/10/2016TRAN THI NGOC ANH GIUP MS 2320200,00019/10/2016NGUYEN NGOC HAN GIUP MS 23201,500,00019/10/2016NGUYEN KHANH PHUONG GIUP MS 2320500,00019/10/2016NGUYEN KHANH PHUONG GIUP MS 2319500,00019/10/2016HA VAN TU GIUP MS 2321100,00019/10/2016DAM THI ANH THU GIUP MS 2319500,00019/10/2016DAM THI ANH THU GIUP MS 23202,000,00019/10/2016THANH TRAN VA HIEN PHAM GUP MS 2320200,00019/10/2016NGUYEN THI HONG NHUNG GIUP MS 2320200,00019/10/2016NGUYEN BA HOANG GIUP MS 2320200,00019/10/2016NGUYEN THI THU THAM GIUP MS 2319100,00019/10/2016NGUYEN THI THU THAM GIUP MS 2311100,00019/10/2016DOAN VAN KIEM GIUP MS 2320500,00019/10/2016PHAM KIM HUONG GIUP MS 2319400,00019/10/2016BUI THU HUONG GIUP MS 2319100,00019/10/2016NGUYEN VAN QUY GIUP MS 23202,000,00019/10/2016NGUYEN DANH THANG GIUP MS 2320500,00019/10/2016DINH XUAN VINH GIUP MS 23202,000,00019/10/2016NGUYEN NGOC BAO KHANH GIUP MS 2319200,00019/10/2016NGUYEN NGOC BAO KHANH GIUP MS 2318200,00019/10/2016NGUYEN NGOC BAO KHANH GIUP MS 2321200,00019/10/2016NGUYEN THANH SON GIUP MS 23201,000,00019/10/2016DOAN THI THANH THUY GUIP MS 2319200,00019/10/2016PHAN THI BANG QUYEN GIUP MS 2320500,00019/10/2016DOAN NGUYEN BAO THU GIUP MS 2318500,00019/10/2016BUI THI NGOC BICH GIUP MS 2319200,00019/10/2016HOANG THU TRANG GIUP MS 2320500,00019/10/2016NGUYEN HONG NHUNG GIUP MS 23191,000,00019/10/2016DO THUY NGA GIUP MS 2321300,00019/10/2016PHAM LE TUYET MINH GIUP MS 2320500,00019/10/2016PHAM KHANH SON GUP MS 23211,000,00019/10/2016VU THI QUYEN GIUP MS 2321150,00019/10/2016NGUYEN NGOC HOANG YEN GIUP MS 23201,000,00019/10/2016TRAN TUAN ANH GIUP MS 23201,000,00019/10/2016TRUONG PHAN LAN ANH GIUP MS 21200,00019/10/2016VU TRUNG KIEN GIUP MS 2320100,00019/10/2016LE VIET THANG GIUP MS 2295250,00019/10/2016LE VIET THANG GIUP MS 2300250,00019/10/2016LE VIET THANG GIUP MS 2303250,00019/10/2016LE VIET THANG GIUP MS 2318250,00019/10/2016NGUYEN THI THUY NGA GIUP MS 232150,00019/10/2016TRINH THI HOAI GIUP MS 2320500,00019/10/2016PHAN HUU SANG GIUP MS 2321100,00019/10/2016PHAN TUYET MAI GIUP MS 2318100,00019/10/2016VU DUC HOANG GIUP MS 2320400,00019/10/2016NGUYEN HONG PHUONG GIUP MS 2321200,00019/10/2016NGUYEN HONG PHUONG GIUP MS 2320200,00019/10/2016HIEU NGHIA GIUP MS 232110,00019/10/2016HIEU NGHIA GIUP MS 232010,00019/10/2016DOAN XUAN VUONG GUP MS 2320200,00019/10/2016NGUYEN THI HUE IGUP MS 2320200,00019/10/2016SOO BONG SWEET GIUP MS 2320200,00019/10/2016PHAM THI VAN ANH GIUP MS 2319100,00019/10/2016NGUYEN MINH NGUYET GIUP MS 2318300,00019/10/2016HOANG DUC HAI GIUP MS 2320300,00019/10/2016TRAN LE MINH GIUP MS 2321300,00019/10/2016LE PHUONG THAO GIUP MS 2320300,00019/10/2016NGUYEN THI XUAN DUNG GIUP MS 2320300,00019/10/2016NGUYEN NGOC THANG GIUP MS 2320500,00019/10/2016HO LE VI GIUP MS 2320100,00019/10/2016NGUYEN VAN VU GIUP MS 2320200,00019/10/2016LE THANH SUU GIUP QNA200,00019/10/2016NGUYEN NHAT MINH GIUP MS 23201,000,00020/10/2016BUI THI NGAN GIUP MS 2320200,00020/10/2016NGUYEN NGOC YEN GIUP QNA100,00020/10/2016TRAN THI DIEU HIEN GIUP MS 2319100,00020/10/2016NGUYEN NAM PHONG GUP MS 2320100,00020/10/2016QUAN CHAN DIEU GIUP MS 2322500,00020/10/2016TRAN THI PHUONG GIUP QNA500,00020/10/2016THANH SON GIUP MS 2322300,00020/10/2016DANG TRAN TRUC HA GUP MS 2320600,00020/10/2016NGUYEN THANH DIEP IGUP MS 2320500,00020/10/2016PHAM VY ANH GIUP MS 2322500,00020/10/2016NGUYEN THI THUY HANG, MAI DANH HUNG GIUP MS 23201,000,00020/10/2016PHAM THI LE NA GIUP MS 2319100,00020/10/2016PHAM THI LE NA GIUP MS 2318100,00020/10/2016NGUYEN THI NGOC THU GIUP MS 2317100,00020/10/2016NGUYEN THI NGOC THU GIUP MS 2318100,00020/10/2016NGUYEN THI NGOC THU GIUP MS 2319100,00020/10/2016BUI THI THANH HUYEN GIUP QNA100,00020/10/2016HA PHI GIUP MS 23191,000,00020/10/2016HA PHI GIUP MS 2321500,00020/10/2016NGUYEN THI BICH HOA GIUP MS 2320500,00020/10/2016PHAM NGOC HIEN GIUP MS 2320500,00020/10/2016BAN SURI GIUP MS 2320300,00020/10/2016BU VAN ANH GIUP MS 23201,000,00020/10/2016CHU MANH TUNG GIUPO MS 23201,200,00020/10/2016PHAM THI HUONG GIUP MS 2320100,00020/10/2016PHAM DINH THANG GIUP MS 23201,000,00020/10/2016BAN DOC GIUP MS 2320400,00020/10/2016BAN DOC GIUP MS 2319500,00020/10/2016PHAN THI HONG HA GIUP MS 2320200,00020/10/2016TA VIET TAI GIUP QNA200,00020/10/2016VU THI TUYET HONG GIUP MS 2319200,00020/10/2016NGUYEN BAO TRUNG GIUP MS 2319100,00020/10/2016NGUYEN BAO TRUNG GIUP MS 2321100,00020/10/2016NGUYEN THI PHUONG LINH GIUP MS 2320200,00020/10/2016TO MINH NHAT GIUP MS 2237300,00020/10/2016TO MINH NHAT GIUP MS 2307200,00020/10/2016TO MINH NHAT GIUP MS 2319200,00020/10/2016HOANG CHI TRUNG GUP MS 2319500,00020/10/2016PHAN NGOC HUNG GIUP MS 2319100,00020/10/2016PHAN NGOC HUNG GIUP MS 2320100,00020/10/2016PHAN NGOC HUNG GIUP MS 2321100,00020/10/2016NGUYEN HONG PHUONG GIUP MS 2322200,00020/10/2016HIEU NGHIA GIUP MS 232210,00020/10/2016BAN DOC GUP MS 2322100,00020/10/2016BAN DOC GIUP MS 231950,00020/10/2016BAN DOC GIUP MS 2322100,00020/10/2016PHAM THI THU HUONG GIUP MS 2319300,00020/10/2016DUONG TUAN TRINH GIUP MS 2320100,00020/10/2016PHAM DUC THANG GIUP MS 2320500,00020/10/2016BE DIEU MINH GIUP MS 2320200,00020/10/2016NGUYEN KHOA DANH GIUP MS 23221,000,00020/10/2016TA QUOC VIET GIUP MS 2322200,00020/10/2016TRANNAM THANG GIUP MS 2320500,00020/10/2016PHAM VAN HUNG GIUP MS 2319200,00020/10/2016THUY GIUP MS 2320500,00020/10/2016LE THANH PHONG GIUP MS 2322200,00020/10/2016NGUYEN ANH, LAN ANH, BICH VAN GIUP MS 23201,300,00020/10/2016BAN DOC GIUP MS 2319500,00020/10/2016NGUYEN MANH HUNG GIUP MS 2322100,00020/10/2016KHUAT THI THANH VAN GIUP MS 2280200,00020/10/2016KHUAT THI THANH VAN GIUP MS 2286200,00020/10/2016KHUAT THI THANH VAN GIUP MS 2291Q200,00020/10/2016KHUAT THI THANH VAN GIUP MS 22913200,00020/10/2016KHUAT THI THANH VAN GIUP MS 2321200,00020/10/2016KHUAT THI THANH VAN GIUP MS 2320700,00020/10/2016LE VIET BA GIUP MS 2320100,00020/10/2016NGUYEN DINH VINH GIUP MS 2320500,00020/10/2016TRAN VUONG KHANG GIUP MS 2307700,00020/10/2016TRAN VUONG KHANG GIUP MS 2319600,00020/10/2016TRAN VUONG KHANG GIUP MS 2297700,00020/10/2016NGUYEN CAO PHONG GIUP MS 2320200,00020/10/2016NHUNG NGUOI DAM ME GYM NGUYEN MINH QUANG SON HOEU LOC HUNG DAT GIUP MS 23201,670,00020/10/2016TRAN THUY QUYNH GIUP MS 2320100,00020/10/2016NGUYEN THI HUONG GIUP MS 2320200,00020/10/2016PHAM BICH NGOC GIUP MS 2320400,00020/10/2016NGUYEN THI THANH HA GIUP MS 2321200,00020/10/2016NGUYEN THI THANH HA GIUP MS 2319200,00020/10/2016PHAM THI HA PHUONG GIUP MS 2320196,70020/10/2016PHAN TRUNG KIEN GIUP MS 2320500,00020/10/2016LY PHUC CUONG GIUP MS 2320300,00020/10/2016NGUYEN THI KIM CUC GIUP MS 23205,000,00020/10/2016BAN DOC GIUP MS 2322200,00020/10/2016TRAN QUY LINH GIUP MS 2320100,00020/10/2016BAN DOC GIUP MS 2308300,00020/10/2016BAN DOC GIUP MS 2322200,00020/10/2016BAN DOC GIUP MS 2319300,00020/10/2016HOANG MANH DUC GIUP MS 23201,000,00020/10/2016DANG THU HANG GIUP MS 2322100,00020/10/2016LE DUC ANH GIUP QNA100,00020/10/2016BAN DOC GIUP MS 2320200,00020/10/2016NGUYEN THI KIEU DIEM GIUP MS 2320200,00020/10/2016NGUYEN THI HOA GIUP MS 2318100,00020/10/2016DINH ANH TUAN GIUP MS 2322100,00020/10/2016DINH ANH TUAN GIUP MS 2319100,00020/10/2016CONG TY CPDT VNINVEST GIUP MS 232020,000,00020/10/2016TRAN LAN HUONG GIUP MS 2322500,00020/10/2016TRAN VAN DUNG GIUP MS 232150,00020/10/2016MINH TUNG GIUP MS 232250,00020/10/2016PHAM TIEN MANH GIUP MS 2322300,00020/10/2016NGUYEN THI THANH XUAN GIUP MS 2320100,00020/10/2016NGUYEN NGOC BINH GUP MS 232250,00020/10/2016PHUNG VAN KHOA GIUP MS 2322200,00020/10/2016DANG QUYNHNHU GIUP MS 2319200,00020/10/2016DANG QUYNHNHU GIUP MS 2318200,00020/10/2016DANG QUYNHNHU GIUP MS 2315200,00020/10/2016NGUYEN TRONG HUY GIUP MS 2320400,00020/10/2016VUONG MY PHUNG GIUP MS 2320200,00020/10/2016NGUYEN QUOC HUY GUP MS 2308200,00020/10/2016NGUYEN TIEN DUNG GIUP MS 2320500,00020/10/2016PHAM THI HAI VAN GIUP MS 2319200,00020/10/2016NGUYEN VU HA GUP MS 2182500,00020/10/2016DANG THI PHUONG LIEN GIUP MS 23215,000,00021/10/2016NGUYEN THI QUYNH NHU GIUP MS 2317100,00021/10/2016NGUYEN THI QUYNH NHU GIUP MS 2313100,00021/10/2016NGUYEN THI QUYNH NHU GIUP MS 2322100,00021/10/2016CHAU THI YEN GIUP MS 23192,000,00021/10/2016CHAU THI YEN GIUP MS 23201,000,00021/10/2016CHAU THI YEN GIUP MS 23212,000,00021/10/2016CHAU THI YEN GIUP MS 23221,000,00021/10/2016CHAU THI YEN GIUP MS 23232,000,00021/10/2016CHAU THI YEN GIUP MS 23182,000,00021/10/2016HOANG NGOC NAM GUP QNA200,00021/10/2016LE THI THANH HUYEN GIUP MS 2323200,00021/10/2016BAN DOC GIUP QNA100,00021/10/2016BAN DOC GIUP QNA400,00021/10/2016NGUYEN BINH TRUYEN GIUP MS 14652,000,00021/10/2016PHAN TRANG GIUP MS 2305200,00021/10/2016HUYNH THI PHUONG THAO GIUP MS 23194,000,00021/10/2016HUYNH THI PHUONG THAO GIUP MS 23204,000,00021/10/2016BUI TUAN NAM GIUP MS 2320500,00021/10/2016NGUYEN THI PHUONG THAO GIUP MS 2319200,00021/10/2016NGUYEN DINH HUY GIUP MS 2323200,00021/10/2016NGUYEN THI KIM LOAN GIUP MS 23231,000,00021/10/2016NGO ANH DUONG GIUP MS 2323100,00021/10/2016VO DINH NGOC GIUP MS 2323200,00021/10/2016VU THI T HU GIUP MS 2323100,00021/10/2016BAN DOC GIUP QNA1,000,00021/10/2016NGO TRUONG HAI GIUP MS 23203,000,00021/10/2016BAN DOC GIUP MS 2308500,00021/10/2016THUY GIUP MS 2320100,00021/10/2016BAN DOC GIUP MS 2323100,00021/10/2016MINH TUNG GIUP MS 232050,00021/10/2016BAN DOC GIUP MS 2323200,00021/10/2016BAN DOC GIUPMS 23232,000,00021/10/2016BAN DOC GIUPMS 2323100,00021/10/2016BAN DOC GIUPMS 2323100,00021/10/2016BAN DOC GIUPMS 2319100,00021/10/2016BAN DOC GIUPMS 2320100,00021/10/2016NGUYEN NGOC BINH GIUP MS 2323100,00021/10/2016VU THI HOANG ANH GIUP MS 2323100,00021/10/2016LE THU HA GIUP MS 23231,000,00021/10/2016NGUYEN THANH TUAN GIUP MS 232350,00021/10/2016DIEP HOANG HA GIUP MS 2323100,00021/10/2016DIEP HOANG HA GIUP MS 2321100,00021/10/2016PHAM LE NHAT KHANH GIUP MS 2319200,00021/10/2016DAO DUY NANG GIUP MS 2323200,00021/10/2016TRIEU SOC THANH GIUP MS 2323500,00021/10/2016VAN TAM HUNG GIUP MS 2322500,00021/10/2016CAO THANH TRUNG, NGOC AN GIUP MS 23201,100,00021/10/2016NGO THI HUONG GIUP MS 2319300,00021/10/2016VO TU ANH GIUP MS 23205,000,00021/10/2016TRAN THANH HAI GIUP MS 2323500,00021/10/2016PHAN CHAU TUAN GIUP MS 2319200,00021/10/2016CHAU VU TUAN DAT GIUP MS 2320100,00021/10/2016CHAU VAN PHONG GIUP MS 2322100,00021/10/2016NGUYEN VAN KHANH GIUP MS 2320100,00021/10/2016DO MINH GIUP MS 2322500,00021/10/2016BUI TRIEU XA GIUP MS 2318300,00021/10/2016BUI TRIEU XA GIUP MS 2322300,00021/10/2016BUI TRIEU XA GIUP MS 2319200,00021/10/2016BUI TRIEU XA GIUP MS 2317150,00021/10/2016BUI TRIEU XA GIUP MS 2323100,00021/10/2016BUI TRIEU XA GIUP MS 231650,00021/10/2016BUI TRIEU XA GIUP MS 232150,00021/10/2016PHUC ANH MINH GIUP MS 23231,000,00021/10/2016TA THI HONG YEN GIUP MS 2323500,00021/10/2016TRAN VAN THANH GIUP MS 2323100,00021/10/2016PHAM GIANG NAM GIUP MS 2323510,00021/10/2016DUONG HUU THANH GIUP MS 2323200,00021/10/2016VO THI NGOC NHI GIUP MS 23231,000,00021/10/2016DOAN ANH DUC GIUP MS 23221,500,00021/10/2016NGUYEN HOAI ANH GIUP MS 2323300,00021/10/2016NGUYEN THANH HUONG GIUP MS 2323800,00021/10/2016LE THI THANH HOA GIUP MS 2323100,00021/10/2016HA THI THU HIEN GIUP MS 2317200,00021/10/2016HA THI THU HIEN GIUP MS 2323300,00021/10/2016NGUYEN TRAN THANH GIANG GIUP MS 2323300,00021/10/2016TRINH MINH CHIEU GIUP MS 2323100,00021/10/2016NGUYEN THI HUE IGUP MS 2311100,00021/10/2016NGUYEN THI HUE IGUP MS 2314100,00021/10/2016NGUYEN THI HUE IGUP MS 2319100,00021/10/2016NGUYEN THI HUE IGUP MS 2320100,00021/10/2016NGUYEN THI HUE IGUP MS 2323100,00021/10/2016NGUYEN VAN THUY GIUP MS 2323100,00021/10/2016TA THI MINH HIEU GIUP MS 2323200,00021/10/2016NGUYEN VAN THUY GIUP MS 2320100,00021/10/2016NGUYEN LINH CHI GIUP MS 2323200,00021/10/2016LAM HO THUY GIUP MS 2319500,00021/10/2016HOANG NGUYEN GIUP MS 2323400,00021/10/2016PHAM DUC ANH GIUP MS 2323100,00021/10/2016VU VAN KHOAT GIUP MS 232320,00021/10/2016NGUYEN THI HONG LY GIUP MS 2319300,00021/10/2016NGUYEN THI HONG LY GIUP MS 2320300,00021/10/2016LE THANH SON GIUP MS 2323100,00021/10/2016LE THI NGUYET THU GIUP MS 23191,000,00021/10/2016VU MINH HAI GIUP MS 2319300,00021/10/2016LE THI NGUYET THU GIUP MS 23201,500,00021/10/2016NGUYEN THU NGA GIUP QNA200,00021/10/2016NGUYEN NAM HAI GIUP MS 2323100,00021/10/2016PHAM THI MUOI GIUP MS 2321700,00021/10/2016DO THI NGOC CHAU GIUP MS 2319100,00021/10/2016NGUYEN THI TRA GIUP MS 2320500,00021/10/2016DINH XUAN LOI GIUP MS 2323200,00021/10/2016HUYNH THI NGOC LAN GIUP MS 2323200,00021/10/2016HOANG THI THANH HUYEN, NGUYEN VAN LINH GIUP MS 2319250,00021/10/2016NGUYEN THI THANH THUY GIUP MS 2314200,00021/10/2016NGUYEN THI THANH THUY GIUP MS 2323100,00021/10/2016HUYNH MINH KHOI GIUP MS 2323300,00021/10/2016TRAN THU HIEN GIUP MS 2323200,00021/10/2016VUONG NGOC MY LINH GIUP MS 23191,000,00021/10/2016BUI THI HAO GIUP MS 2320200,00021/10/2016VUONG, THE, NAM, DUC GIUP MS 23202,400,00021/10/2016NGUYEN HIEU LINH GIUP MS 2323200,00021/10/2016BANH HAI QUANG GUP MS 2323200,00021/10/2016NGUYEN TUAN HIEN GIUP MS 2323100,00021/10/2016PHAM DANG GIUP MS 2320100,00021/10/2016NGUYEN TUN GLINH GIUP MS 2323200,00021/10/2016TRAN HOANG ANH GIUP MS 2323100,00021/10/2016HOANG THI THUY GIUP MS 2323200,00021/10/2016NGO THI THU TRANG GIUP MS 2319200,00021/10/2016LUONG VIET LOC IGUP MS 2323500,00021/10/2016VUONG THI THUY DUONG GIUP MS 2320200,00021/10/2016VO TRONG KHANH GIUP MS 2323500,00021/10/2016NGUYEN DUY VIET GIUP MS 2323500,00021/10/2016NGUYEN DUY VIET GIUP MS 2321500,00021/10/2016HUYNH LE NGOC VIEN GIUP MS 2323500,00021/10/2016NGUYEN THANH SON GIUP MS 2323300,00021/10/2016HOANG VIET ANH GIUP QNA200,00021/10/2016NGUYEN ANH TUAN GIUP MS 2323150,00021/10/2016VUONG THI THUY DUONG GIUP MS 2323100,00021/10/2016NGUYEN TRUONG SON GIUP MS 2323100,00021/10/2016HOANG MANH TUAN GIUP MS 2323300,00021/10/2016NGUYEN VAN DUNG GIUP MS 2323500,00021/10/2016LAM NGUYEN KHAI GIUP MS 2323200,00021/10/2016DANG THU QUYNH GIUP MS 2320200,00021/10/2016NGUYEN TRAN PHONG GIUP MS 2323500,00021/10/2016NGUYEN THI PHUONG GIUP MS 2323200,00021/10/2016NGUYEN LE PHUONG GIUP MS 2315200,00021/10/2016TRUONG VU HANH GIUP MS 2322500,00021/10/2016TRUONG VU HANH GIUP MS 2323500,00021/10/2016DANG THI MAI LOAN GIUP MS 2323200,00021/10/2016NGUYEN LE PHUONG GIUP MS 2318200,00021/10/2016NGUYEN LE PHUONG GIUP MS 2319200,00021/10/2016QUAN, MINH, KIEN, TOAN GIUP MS 23191,000,00021/10/2016NGUYEN LE PHUONG GIUP MS 2321200,00021/10/2016NGUYEN LE PHUONG GIUP MS 2323200,00021/10/2016NGUYEN CONG HOANG GIUP MS 2322300,00021/10/2016NGUYEN GIA TAM NHA GIUP MS 2323300,00021/10/2016TRUONG THI DONG XUAN GIUP MS 2323100,00021/10/2016LE NGOC LAN GIUP MS 2323100,00021/10/2016TRAN THI THUY HANG IGUP MS 2323100,00021/10/2016TRAN THI THU HIEN GIUP MS 2323200,00021/10/2016VU THI DUNG GIUP MS 2320200,00021/10/2016NGUYEN XUAN VU GIUP MS 2323200,00021/10/2016VU THI THU HA GIUP MS 2320500,00021/10/2016TRAN MINH DUC IGUP QNA300,00021/10/2016NGUYEN THANH HUYEN GIUP MS 2320200,00021/10/2016VU THI HIEN GIUP MS 232350,00021/10/2016TRAN TRANG NHAT GIUP MS 2323100,00021/10/2016TRAN NGOC ANH GIUP MS 2323150,00021/10/2016NGUYEN VAN LUONG GIUP MS 2323500,00021/10/2016LE THI HONG PHUONG GUP MS 2323200,00021/10/2016TRAN THI NHAT ANH GIUP MS 2323100,00021/10/2016TRAN XUAN LINH GIUP MS 231850,00021/10/2016PHAN NGOC HUNG GUP MS 2323100,00021/10/2016NGUYEN HONG PHUONG GIUP MS 2323196,00021/10/2016TRAN XUAN LINH GIUP MS 231950,00021/10/2016HIEU NGHIA GIUP MS 232310,00021/10/2016TRAN XUAN LINH GIUP MS 232250,00021/10/2016NGUYEN QUYNH NGOC GIUP MS 2322250,00021/10/2016HA MINH TUAN GIUP QNA200,00021/10/2016BAN DOC GIUP MS 23203,000,00021/10/2016BAN DOC GIUP MS 2322100,00021/10/2016HUU TUNG GIUP MS 2322100,00021/10/2016DUONG HUU THANH LONG GIUP MS 2322200,00021/10/2016NGUYEN SY HUNG IGUP MS 2322200,00021/10/2016BAN DOC GIUP MS 2320500,00022/10/2016BAN DOC GIUP QNA100,00022/10/2016BAN DOC GIUP MS 2323300,00022/10/2016BAN DOC GIUP MS 2323100,00022/10/2016BAN DOC GIUP QNA200,00022/10/2016BAN DOC GIUP MS 2323100,00022/10/2016LUONG THI THU HOAN GIUP MS 2323200,00022/10/2016HO THI MINH HUYEN GIUP MS 232050,00022/10/2016NGUYEN HUU VU GIUP QNA200,00022/10/2016NGUYEN NGOC BINH GIUP MS 232450,00022/10/2016MAC THI THAM GIUP MS 232350,00022/10/2016MAC THI THAM GIUP MS 2320100,00022/10/2016PHAN THANH HOA GIUP QNA200,00022/10/2016NGUYEN THI MY DUNG GIUP MS 2323100,00022/10/2016NGUYEN THI MY DUNG GIUP MS 2324100,00022/10/2016PHAN THI MY DUNG GIUP MS 2323500,00022/10/2016HOANG DUONG HAI GIUP MS 2323500,00022/10/2016HOANG DUONG HAI GIUP MS 23202,000,00022/10/2016ME CON LO NGHE GIUP MS 2323100,00022/10/2016ME CON LO NGHE GIUP MS 2324100,00022/10/2016NGUYEN THI KIEU DIEM GIUP MS 2324200,00022/10/2016HUYNH ANH TUAN GIUP MS 2320350,00022/10/2016LE DUC ANH GIUP QNA50,00022/10/2016GIA DINH BE TRI VA 2 BEN NOI NGOAI GIUP MS 2323300,00022/10/2016PHAM DUC KHANH GIUP MS 2323200,00022/10/2016NGUYEN THI NHUNG GIUP MS 2308200,00022/10/2016LE THI VAN GIUP MS 2320500,00022/10/2016DAO VAN HUNG GIUP MS 2323, 232480,00022/10/2016PHUONG NGHI GIUP MS 23231,000,00022/10/2016NGUYEN THI HONG MINH GIUP MS 2323100,00022/10/2016NGUYEN THI HOAI MY GIUP MS 2320100,00022/10/2016LE THU HANG GIUP MS 232450,00022/10/2016TRAN HOANG ANH GIUP MS 2324100,00022/10/2016LUU THANH LONG GIUP MS 2323200,00022/10/2016NGUYEN CANH TOAN GIUP MS 2323200,00022/10/2016TRAN THO BINH GIUP MS 2323200,00022/10/2016TRAN ANH KHOA GIUP MS 2323500,00022/10/2016QUACH DINH PHUC GIUP MS 2323100,00022/10/2016DINH THI CONG NUONG GIUP MS 2324300,00022/10/2016NGUYEN HOANG ANH GIUP MS 2323100,00022/10/2016PHUNG BAO TRAN GIUP MS 2323100,00022/10/2016PHAM VIET BACH GIUP MS 23201,000,00022/10/2016TRUONG THI HOAI THO GIUP MS 2324200,00022/10/2016TRUONG THI HOAI THO GIUP MS 2322200,00022/10/2016NGUYEN THAI HONG IGUP MS 2323300,00022/10/2016LE THANH TRUC GIUP MS 2320500,00022/10/2016TRINH NGOC DUY GIUP MS 2323200,00022/10/2016NGUYEN THI HOANG THUY GIUP MS 2323200,00022/10/2016NGO THI KIM TUYET GIUP MS 2319300,00022/10/2016HIEU NGHIA GIUP MS 232410,00022/10/2016TU VIEN TRUNG GIUP MS 2323300,000 PHUNG PHUOC LINH GIUP MS 2323500,000 Bạn đọc ủng hộ qua ngân hàng Vietinbank\n\t\t\ttừ ngày 16 đến 22/10/2016 16/10/2016Ban doc TK 711A58754717 giup MS 2316300,00017/10/2016Ban doc TK 711A07437638 giup MS 2318100,00017/10/2016Huynh Khanh Linh giup MS 2319300,00017/10/2016Tran Quang Dung giup MS 22921,000,00017/10/2016Tran Quang Dung giup MS 22991,000,00017/10/2016Chu T Hong Thao ung ho QNA50,00017/10/2016Ban doc TK 711A11041523 giup MS 2318200,00017/10/2016Ban doc TK 711A53123424 giup MS 231850,00017/10/2016Ban doc TK 711AA6321292 giup MS 2318500,00017/10/2016Ban doc TK 711A60945901 giup MS 2318200,00017/10/2016Le T Hai Ha giup MS 2318300,00017/10/2016Nguyen T Hue giup MS 2314100,00017/10/2016Nguyen T Hue giup MS 2315100,00017/10/2016Do Cong Nguyen giup MS 2317100,00017/10/2016Nguyen Minh Quan giup MS 231288,00017/10/2016Nguyen Minh Quan giup MS 231688,00017/10/2016Nguyen T My Dieu giup MS 2318200,00017/10/2016Nguyen T Huong giup MS 2315200,00017/10/2016Le T Kim Dung giup MS 22772,000,00017/10/2016Le T Kim Dung giup MS 23052,000,00017/10/2016Ban doc tai 142 Cn Hai Ba Trung giup MS 2314200,00017/10/2016Ban doc tai 324 Cn Quang Trung giup MS 23185,000,00017/10/2016PHN Thi Thu Huong giup MS 2293100,00017/10/2016PHN Thi Thu Huong giup MS 2294100,00017/10/2016PHN Thi Thu Huong giup MS 2295100,00017/10/2016PHN Thi Thu Huong giup MS 2290100,00017/10/2016PHN Thi Thu Huong giup MS 2291100,00017/10/2016PHN Thi Thu Huong giup MS 2283100,00017/10/2016PHN Thi Thu Huong giup MS 2272100,00017/10/2016PHN Thi Thu Huong giup MS 2269100,00017/10/2016PHN Thi Thu Huong giup MS 2298100,00017/10/2016PHN Thi Thu Huong giup MS 2305100,00017/10/2016PHN Thi Thu Huong giup MS 2313100,00017/10/2016PHN Thi Thu Huong giup MS 2314100,00017/10/2016PHN Thi Thu Huong giup MS 2315100,00017/10/2016PHN Thi Thu Huong giup MS 2318100,00017/10/2016Ban doc tai 328 Cn Lang Hoa Lac giup MS 2312200,00017/10/2016Mai T Phuong Thuy ung ho QNA200,00017/10/2016Tran Vu yen Ngoc giup MS 2309200,00017/10/2016Tran Vu yen Ngoc giup MS 2310200,00017/10/2016Tran Vu yen Ngoc giup MS 2311200,00017/10/2016Chau Luu Ngoc Khanh giup MS 2318100,00018/10/2016Vu Phu Quynh giup MS 2319200,00018/10/2016Ban doc TK 711AA3176484 giup MS 2319200,00018/10/2016Ban doc TK 711A25242213 giup MS 2319100,00018/10/2016Ban doc TK 711A22291868 giup MS 2319200,00018/10/2016Nguyen Hong Trang giup MS 2319500,00018/10/2016Ban doc TK 711A13449237 giup MS 2319100,00018/10/2016Ban doc TK 711AA1617401 giup MS 2319200,00018/10/2016Ban doc TK 711A68711284 giup MS 231950,00018/10/2016Ban doc TK 711A79399446 giup MS 2319200,00018/10/2016Nguyen Tuan Long ung ho QNA500,00018/10/2016Ban doc TK 711A53123424 giup MS 231750,00018/10/2016Ban doc TK 711A60945901 giup MS 2319200,00018/10/2016Chau Ta Nguyen Khang giup MS 23201,000,00018/10/2016Le Van Hung giup MS 2315100,00018/10/2016Le Van Hung giup MS 2316100,00018/10/2016Le Van Hung giup MS 2317100,00018/10/2016Le Van Hung giup MS 2318100,00018/10/2016Le Van Hung giup MS 2319100,00018/10/2016Hoang Phuong giup MS 2318300,00018/10/2016Tran Thuy Thanh Phuong giup MS 2319200,00018/10/2016Dong Thai Hoa giup MS 2319200,00018/10/2016Pham The Nghiep giup MS 2319100,00018/10/2016Ha Hoai Nam giup MS 23185,000,00018/10/2016Be Cao Dinh An Binh + Cao Dinh Binh An giup MS 2282100,00018/10/2016Be Cao Dinh An Binh + Cao Dinh Binh An giup MS 2289100,00018/10/2016Be Cao Dinh An Binh + Cao Dinh Binh An giup MS 2313100,00018/10/2016Be Cao Dinh An Binh + Cao Dinh Binh An giup MS 2314100,00018/10/2016Be Cao Dinh An Binh + Cao Dinh Binh An giup MS 2319100,00018/10/2016Nguyen Hue giup MS 2319100,00018/10/2016Tran Van Giang giup MS 2319200,00018/10/2016Nguyen T Thanh Hien giup MS 2319200,00018/10/2016Tra Xuan Binh giup MS 20165,00018/10/2016Tra Xuan Binh giup MS 23195,00018/10/2016Dinh Quoc Thanh giup MS 23182,500,00018/10/2016Nguyen T Thu Van giup MS 2319100,00019/10/2016Ban doc TK 711A01789862 giup MS 2321200,00019/10/2016Ha T Hong Hai giup MS 2320300,00019/10/2016Dinh Thanh Sang giup MS 2320200,00019/10/2016Ban doc TK 711A17029516 giup MS 2320100,00019/10/2016Ban doc TK 711A53123424 giup MS 231950,00019/10/2016Ban doc TK 711A80268033 giup MS 2321200,00019/10/2016Ban doc TK 711A01357596 giup MS 23202,000,00019/10/2016Ban doc TK 711A72447371 giup MS 2320100,00019/10/2016Ban doc TK 711A05293935 giup MS 2320500,00019/10/2016Ban doc TK 711A59283251 giup MS 2319250,00019/10/2016Ban doc TK 711A59283251 giup MS 2306250,00019/10/2016Ban doc TK 711A06578713 giup MS 23201,000,00019/10/2016Nguyen Van Tuan ung ho QNA200,00019/10/2016Ban doc TK 711A00469232 giup MS 2319200,00019/10/2016Nguyen Truong Minh giup MS 2318300,00019/10/2016Nguyen Dinh Dung ung ho QNA50,00019/10/2016Nguyen T Minh Loan giup MS 23201,000,00019/10/2016Dao Viet Thanh giup MS 2320300,00019/10/2016Le T Thuy giup MS 23202,500,00019/10/2016Tran Dai Nghia giup MS 2318100,00019/10/2016Tran Dai Nghia giup MS 2319100,00019/10/2016Tran Dai Nghia giup MS 2321100,00019/10/2016Hoang T Hong Nhung giup MS 2320500,00019/10/2016Tong Khanh Toan giup MS 2317500,00019/10/2016Tran T Ninh Nham giup MS 2288200,00019/10/2016Tran T Ninh Nham giup MS 2289100,00019/10/2016Tran T Ninh Nham giup MS 2292200,00019/10/2016Tran T Ninh Nham giup MS 2300100,00019/10/2016Tran T Ninh Nham giup MS 2305100,00019/10/2016Tran T Ninh Nham giup MS 2306200,00019/10/2016Cty CP Co dien XNK Toan Cau giup MS 23202,000,00019/10/2016Do Thu Huong giup MS 23201,000,00019/10/2016Vu Duc Hung giup MS 231910,000,00019/10/2016Do Minh Phuc giup MS 232025,000,00019/10/2016Ban doc tai 282 CN Bac Ninh giup MS 2319200,00019/10/2016Cty TNHH TP Nam Ha Long giup MS 23202,000,00019/10/2016Cty TNHH Ky thuat dien Viet Han giup MS 232010,000,00019/10/2016Vu T Kim Oanh giup MS 2292200,00020/10/2016Ban doc TK 711A53123424 giup MS 232150,00020/10/2016Ban doc TK 711AC6514412 giup MS 2322200,00020/10/2016Ban doc TK 711A60945901 giup MS 2322200,00020/10/2016Ban doc TK 711AB7131944 giup MS 2322300,00020/10/2016Ban doc TK 711A22374042 ung ho QNA100,00020/10/2016Le Thanh Trung giup MS 2322300,00020/10/2016Nguyen Dinh Dung giup MS 23201,000,00020/10/2016Nguyen T My Dieu giup MS 2319200,00020/10/2016Vien NC va Ho tro thu nghiem lam sang Vac xin va Sinh pham y te giup MS 23206,000,00021/10/2016Ban doc TK 711AC2274611 giup MS 2323200,00021/10/2016Ban doc TK 711A47970732 giup MS 2322300,00021/10/2016Vo Le Xuan Huong ung ho QNA100,00021/10/2016Ban doc TK 711A47970732 giup MS 2319200,00021/10/2016Dang Son Tung giup MS 2319100,00021/10/2016Ban doc TK 711A53123424 giup MS 232250,00021/10/2016Nguyen T Hang giup MS 2320100,00021/10/2016Nguyen T Doan giup MS 2323200,00021/10/2016Ban doc TK 711A38836993 giup MS 2323200,00021/10/2016Ban doc TK 711A77448571 giup MS 2323200,00021/10/2016Ban doc TK 711AD2557573 giup MS 2319500,00021/10/2016Ban doc TK 711A01399656 giup MS 2323100,00021/10/2016Nguyen Khac Truong giup MS 232350,00021/10/2016Ban doc TK 711A53123424 giup MS 232350,00021/10/2016Tran Thu Huong ung ho QNA300,00021/10/2016Ban doc TK 711AD2557573 giup MS 2323300,00021/10/2016Ban doc TK 711A74692193 giup MS 2323200,00021/10/2016Ban doc TK 711A76856415 giup MS 2323300,00021/10/2016Ban doc TK 711A07851973 giup MS 2323100,00021/10/2016Nguyen T Thuy giup MS 2323500,00021/10/2016Nguyen T Thuy giup MS 2319500,00021/10/2016Le Thanh Trung giup MS 2323200,00021/10/2016Tra Xuan Binh ung ho QNA10,00021/10/2016Tra Xuan Binh giup MS 232110,00021/10/2016Nguyen T Thanh Thoa giup MS 2322200,00021/10/2016Ban doc tai 800 CN Vinh Long giup MS 23201,000,00021/10/2016Phan Trinh giup MS 2319400,00021/10/2016Phan Trinh giup MS 2318400,00021/10/2016Phan Trinh giup MS 2315400,00021/10/2016Phan Trinh giup MS 2313400,00021/10/2016Phan Trinh giup MS 2322400,00021/10/2016Tong T Bich Loan giup MS 2320300,00021/10/2016Ban doc tai 944 Cn 12 TP HCM giup MS 2320500,00021/10/2016Tra Xuan Binh giup MS 232010,00021/10/2016Bui To Trinh giup MS 2288200,00021/10/2016Bui To Trinh giup MS 2292200,00021/10/2016Bui To Trinh giup MS 2294200,00021/10/2016Bui To Trinh giup MS 2295200,00021/10/2016Bui To Trinh giup MS 2306200,00021/10/2016Bui To Trinh giup MS 2319200,00021/10/2016Bui To Trinh giup MS 2321200,00021/10/2016Bui To Trinh giup MS 2323200,00022/10/2016Ban doc TK 711A21577645 giup MS 2323500,00022/10/2016Cty Nha an Toan giup Ms 23204,000,00022/10/2016Ban doc TK 711A41256773 giup MS 232450,00022/10/2016Ban doc TK 711A86216057 giup MS 2320200,00022/10/2016Anh chi Long - Phuong giup MS 2320400,00022/10/2016Ban doc TK 711A32920539 giup MS 2323150,00022/10/2016Ban doc TK 711A86051702 giup MS 1203200,000 Bạn đọc ủng hộ qua ngân hàng Vietinbank\n\t\t\tTrực tuyến từ ngày 16 đến 22/10/2016 16/10/2016Ban doc TK 711A21662006 giup MS 231650,00016/10/2016Ban doc TK 711A67111164 ung ho QNA100,00016/10/2016Ban doc TK 711A32906392 giup MS 231750,00016/10/2016Ban doc TK 711AC8089624 giup MS 231750,00016/10/2016Ban doc TK 711AC6178889 ung ho QNA10,00017/10/2016Ban doc TK 711A01922301 giup MS 2316300,00017/10/2016Ban doc TK 711AB6612374 giup MS 231750,00017/10/2016Ban doc TK 711A71902314 giup MS 231850,00017/10/2016Ba Ho T Nga giup MS 2317200,00017/10/2016Ba Ho T Nga giup MS 2318200,00017/10/2016Ba Ho T Nga giup MS 2290200,00017/10/2016Ba Ho T Nga giup MS 2314200,00017/10/2016Ba Ho T Nga giup MS 2316200,00017/10/2016Ban doc TK 711A32906392 giup MS 231850,00017/10/2016Pham Gia Tu giup MS 230750,00017/10/2016Pham Gia Tu giup MS 230850,00017/10/2016Pham Gia Tu giup MS 230950,00017/10/2016Ban doc TK 711A89534105 giup MS 2318100,00017/10/2016Le Hoang Linh giup MS 231850,00017/10/2016Ban doc TK 711A11369358 giup MS 2318200,00017/10/2016Ban doc TK 711A61693341 giup MS 2318500,00017/10/2016Ban doc TK 711A00092073 giup MS 2317200,00017/10/2016Ban doc TK 711A00092073 giup MS 2318200,00017/10/2016Ban doc TK 711AC8098561 giup MS 231050,00017/10/2016Nguyen Quang Ngoc giup MS 2318500,00018/10/2016Ban doc TK 711A64755947 giup MS 231950,00018/10/2016Nguyen Tien Quyen giup MS 2314100,00018/10/2016Nguyen Tien Quyen giup MS 2315100,00018/10/2016Nguyen Tien Quyen giup MS 2316100,00018/10/2016Nguyen Tien Quyen giup MS 2317100,00018/10/2016Nguyen Tien Quyen giup MS 2318100,00018/10/2016Nguyen Tien Quyen giup MS 2319100,00018/10/2016Ban doc TK 711A00747342 giup MS 2319100,00018/10/2016Ban doc TK 711A00747342 giup MS 2300100,00018/10/2016Ban doc TK 711A34121027 giup MS 2312100,00018/10/2016Ban doc TK 711A34649341 ung ho QNA200,00018/10/2016Ban doc TK 711A56005211 giup MS 2319300,00018/10/2016Ban doc TK 711A89534105 giup MS 2319100,00018/10/2016Ban doc TK 711A32906392 giup MS 231950,00018/10/2016Ban doc TK 711A44189884 giup MS 2319100,00018/10/2016Ban doc TK 711A16748172 giup MS 231950,00018/10/2016Ban doc TK 711A44189884 giup MS 2317100,00018/10/2016Ban doc TK 711A16748172 giup MS 231850,00018/10/2016P. Hoa + P. Anh giup MS 2319300,00018/10/2016Ban doc TK 711A15153911 giup MS 2319200,00018/10/2016Ban doc TK 711A00357808 giup MS 2319200,00018/10/2016Do T Anh Ngoc giup MS 2319200,00018/10/2016Ban doc TK 711A19721513 giup MS 2308100,00018/10/2016Ban doc TK 711A19721513 giup MS 2310100,00018/10/2016Ban doc TK 711A19721513 giup MS 2312100,00018/10/2016Ban doc TK 711A19721513 giup MS 2317100,00018/10/2016Ban doc TK 711A19721513 giup MS 231850,00018/10/2016Ban doc TK 711A19721513 giup MS 231650,00018/10/2016Ban doc TK 711A19721513 giup MS 231550,00018/10/2016Ban doc TK 711A19721513 giup MS 231450,00018/10/2016Ban doc TK 711A19721513 giup MS 231150,00018/10/2016Ban doc TK 711A19721513 giup MS 230950,00018/10/2016Ban doc TK 711A16859481 giup MS 2320300,00018/10/2016Ban doc TK 711A06604322 giup MS 2319200,00019/10/2016Ban doc TK 711A51801205 giup MS 2320500,00019/10/2016Ban doc TK 711A23028971 giup MS 232030,00019/10/2016Nguyen The Hung giup MS 23201,000,00019/10/2016Ban doc TK 711A00143423 giup MS 2320100,00019/10/2016Ban doc TK 711A00143423 giup MS 2320300,00019/10/2016Ban doc TK 711A57062825 giup MS 2321500,00019/10/2016Ban doc TK 711A57062825 giup MS 2319500,00019/10/2016Ban doc TK 711A05374074 giup MS 231920,00019/10/2016Ban doc TK 711A38241223 giup MS 2318200,00019/10/2016Ban doc TK 711A05374074 giup MS 2320100,00019/10/2016Ban doc TK 711A05374074 giup MS 232120,00019/10/2016Ban doc TK 711A09452763 giup MS 2321200,00019/10/2016Ban doc TK 711A05374074 giup MS 231720,00019/10/2016Ban doc TK 711A34347529 giup MS 2320100,00019/10/2016Ban doc TK 711A01922337 giup MS 2319200,00019/10/2016Ban doc TK 711AC7712761 giup MS 2320200,00019/10/2016Ban doc TK 711A24764221 giup MS 2320200,00019/10/2016Ban doc TK 711A17933163 giup MS 2320200,00019/10/2016Ban doc TK 711A32906392 giup MS 232050,00019/10/2016Tom Bi giup MS 2320100,00019/10/2016Huynh Ut Ngo ung ho QNA10,00019/10/2016Ban doc TK 711A00633599 giup MS 2319500,00019/10/2016Nguyen Phuoc Loc giup MS 2320100,00019/10/2016Huy Than giup MS 23201,000,00019/10/2016Lu Lap Phat giup MS 23205,000,00019/10/2016Huynh Y Mi giup MS 23205,000,00019/10/2016Phun Sam Sanh giup MS 2320500,00019/10/2016Ha Ngoc Linh giup MS 2320200,00019/10/2016Nguyen T Ngoc Hieu giup MS 23201,000,00019/10/2016Ban doc TK 711A12919749 giup MS 2319100,00019/10/2016Vo Minh Khoi giup MS 2320300,00019/10/2016Ban doc TK 711A23590531 giup MS 2320500,00019/10/2016Ban doc TK 711A30504724 giup MS 2320100,00020/10/2016Ban doc TK 711A32906392 giup MS 232250,00020/10/2016Ban doc TK 711A39474251 ung ho QNA50,00020/10/2016Ban doc TK 711A21130622 ung ho QNA200,00020/10/2016Ban doc TK 711A11369358 giup MS 2322150,00020/10/2016Ngo Hoang Ngoc Ha ung ho QNA10,00020/10/2016Le Tuan Anh ung ho QNA10,00020/10/2016P. Anh, P. Hoa giup MS 2320300,00020/10/2016Pham Trong Nghia ung ho QNA10,00020/10/2016Ban doc TK 711A12453629 giup MS 2322100,00020/10/2016Doan T Tu giup MS 2320500,00020/10/2016Ban doc TK 711AC0695884 giup MS 23201,000,00020/10/2016Ban doc TK 711A27183569 giup MS 2322200,00020/10/2016Nguyen Quang Khai giup MS 232290,00020/10/2016Ban doc TK 711AA5871342 ung ho QNA10,00121/10/2016Ban doc TK 711A04332493 giup MS 2323300,00021/10/2016Ban doc TK 711A15153911 giup MS 2323200,00021/10/2016Pham Gia Tu giup MS 232350,00021/10/2016Pham Gia Tu giup MS 231250,00021/10/2016Truong Phan Cong Minh ung ho QNA10,00021/10/2016Dao Hong Chuyen giup MS 2323100,00021/10/2016Ban doc TK 711A11369358 giup MS 2323150,00021/10/2016Ban doc TK 711A45236604 giup MS 2319200,00021/10/2016Nguyen The Hien giup MS 2323100,00021/10/2016Ban doc TK 711A23979764 ung ho QNA50,00021/10/2016Ban doc TK 711A06604322 giup MS 2323200,00021/10/2016Dao Ngoc Tuyen giup MS 2320200,00021/10/2016Ban doc TK 711A36233888 giup MS 2316400,00021/10/2016Ban doc TK 711A36233888 giup MS 2317400,00021/10/2016Ban doc TK 711A36233888 giup MS 2318400,00021/10/2016Ban doc TK 711A36233888 giup MS 2319400,00021/10/2016Ban doc TK 711A36233888 giup MS 2321400,00021/10/2016Ban doc TK 711A36233888 giup MS 2322400,00021/10/2016Ban doc TK 711A36233888 giup MS 2323400,00021/10/2016Ban doc TK 711A36233888 giup MS 23202,000,00021/10/2016Ban doc TK 711A20125128 giup MS 2323100,00021/10/2016Ban doc TK 711A32829043 giup MS 2323200,00021/10/2016Ban doc TK 711AD4584427 giup MS 2294100,00022/10/2016Ban doc TK 711A32906392 giup MS 232450,00022/10/2016Ban doc TK 711A57617718 giup MS 2323200,00022/10/2016Ban doc TK 711AB9088118 giup MS 2323200,000 Bạn đọc ủng hộ qua ngân hàng Quân đội\n\t\t\ttừ ngày 16 đến 22/10/2016 17/10/2016Ban doc Dan tri giup 12 ma so tu 2307 den 23182,400,00017/10/2016Nguyen Van Cuong giup MS 23181,400,00017/10/2016Truong Minh Hai ung ho QNA100,00017/10/2016Nguyen Ngoc Linh giup MS 231650,00017/10/2016Nguyen Ngoc Linh giup MS 231750,00017/10/2016Nguyen Thanh Minh giup MS 2318100,00017/10/2016Tran The Ky giup MS 2315700,00017/10/2016Dinh Thi Quynh Phuong giup MS 2314300,00017/10/2016Dinh Thi Quynh Phuong giup MS 2315300,00017/10/2016Dinh Thi Quynh Phuong giup MS 2316300,00017/10/2016Dinh Thi Quynh Phuong giup MS 2317300,00017/10/2016Dinh Thi Quynh Phuong giup MS 2318300,00017/10/2016Vo Thi Van giup MS 2368??50,00017/10/2016Ban doc Dan tri giup MS 2318500,00017/10/2016Nguyen Hoang Hai giup MS 2312100,00017/10/2016Nguyen Hoang Hai giup MS 2318100,00017/10/2016Nguyen Huu Thang giup chi Hoa - Bac Ninh200,00017/10/2016Tran thi Thu giup MS 2317200,00017/10/2016Tran thi Thu giup MS 2318200,00017/10/2016Le Trung Hieu giup MS 2318200,00017/10/2016Le Xuan Trung giup MS 2318500,00018/10/2016Thanh Nguyen giup MS 231850,00018/10/2016Nguyen Viet Thanh giup MS 231950,00018/10/2016Pham thi Thuy Trang giup MS 2319100,00018/10/2016Nguyen Thi Kim Dung giup MS 2319100,00018/10/2016Hoang Duc Dung giup MS 231950,00018/10/2016Pham Vu Hieu giup MS 2319200,00018/10/2016Ban doc Dan tri giup MS 2319150,00018/10/2016Dao thi Hang giup MS 2319200,00018/10/2016Tran Thi Thu giup MS 2319200,00018/10/2016Tran Hoang Nam giup MS 2318200,00018/10/2016Le Thanh Trung giup MS 2319100,00018/10/2016Tran Hoang Nam giup MS 2319200,00018/10/2016Vu Van Tung giup MS 2319300,00018/10/2016Do Thi Bich Thuy giup MS 2312300,00018/10/2016Ho Thi Kim Anh giup Anh Nguyen Van Hoang - Nghe An200,00018/10/2016Nguyen Ngoc Linh giup MS 231850,00018/10/2016Nguyen Thanh Minh giup MS 2319100,00018/10/2016Nguyen Ngoc Linh giup MS 231950,00018/10/2016Ban doc Dan tri giup MS 2319200,00018/10/2016Ban doc Dan tri giup MS 2319300,00018/10/2016Nguyen Hoang Giang giup MS 2319200,00018/10/2016Nguyen Hoang Giang giup MS 2318300,00018/10/2016Do T Bich Thuy giup MS 2306200,00018/10/2016Tran Van manh giup MS 231950,00018/10/2016Nguyen Thi Thu Hang giup MS 2319100,00018/10/2016Do T Bich Thuy giup MS 2320300,00018/10/2016Bui Duc Chuyen giup MS 2320200,00018/10/2016Le Tran Thanh Thuong giup MS 2319100,00019/10/2016Thai Binh Duong giup MS 2320500,00019/10/2016Pham T Thuy Trang giup MS 2320100,00019/10/2016Ng Cong Phi Hung giup MS 2320135,00019/10/2016Le Tran Thanh Thuong giup MS 2317100,00019/10/2016Ban doc Dan tri giup MS 2321200,00019/10/2016Dinh T Quynh Phuong giup MS 2321150,00019/10/2016Dinh T Quynh Phuong giup MS 2319150,00019/10/2016Nguyen Ngoc Linh giup MS 232050,00019/10/2016Nguyen Ngoc Linh giup MS 232150,00019/10/2016Ban doc Dan tri giup be Nguyen Thi Anh Dai - con anh Nguyen Van Hoang - Nghe An200,00019/10/2016Nguyen Minh Tuan giup MS 2320200,00019/10/2016Hoang Anh Dung giup MS 2320200,00019/10/2016Nguyen Tien Dong giup MS 2320300,00020/10/2016Cu Kim Chung giup MS 2322300,00020/10/2016Nguyen Anh Viet giup be Anh Dai200,00020/10/2016Ban doc Dan tri giup MS 2319100,00020/10/2016Ban doc Dan tri giup MS 2321100,00020/10/2016Truong Minh Hai giup MS 2320500,00020/10/2016Tran Duy Bao giup MS 23201,000,00021/10/2016Ban doc Dan tri giup MS 2285100,00021/10/2016Ban doc Dan tri giup MS 2286100,00021/10/2016Ban doc Dan tri giup MS 2297100,00021/10/2016Ban doc Dan tri giup MS 2305100,00021/10/2016Ban doc Dan tri giup MS 2280500,00021/10/2016Ban doc Dan tri giup MS 2291100,00021/10/2016Ban doc Dan tri giup MS 2290100,00021/10/2016Ban doc Dan tri giup MS 2289100,00021/10/2016Ban doc Dan tri giup MS 2288100,00021/10/2016Ban doc Dan tri giup MS 2287100,00021/10/2016Ban doc Dan tri giup MS 2268100,00021/10/2016Truong Duc Lam giup MS 232050,00021/10/2016Le Tran Thanh Thuong giup MS 2322100,00021/10/2016Pham Thi Le giup MS 2323100,00021/10/2016Truong An giup MS 2323200,00021/10/2016Nguyen Minh Duc - Nguyen Thi Anh Nguyet giup MS 2323200,00021/10/2016Nguyen Van Hoan giup MS 23201,000,00021/10/2016Nguyen Thi Bich Hang giup MS 232350,00021/10/2016Hoang Thi Xuan giup MS 232350,00022/10/2016Nguyen Ngoc Khanh giup MS 2320200,00022/10/2016Nguyen Viet Ha giup Yen Nhi50,00022/10/2016Nguyen Manh Hung giup MS 2323200,00022/10/2016Le Bao Tran giup be Yen Nhi200,00022/10/2016Hoang Duc Dung giup MS 232450,00022/10/2016Nguyen Ngan Ha giup Ms 2324200,00022/10/2016Nguyen Hoanh Nam giup MS 23202,000,000 Bạn đọc ủng hộ qua ngân hàng Nông nghiệp\n\t\t\ttừ ngày 16 đến 22/10/2016 17/10/2016Phan Van Nha ung ho QNA200,00017/10/2016Vo Hoang Hung giup MS 2316100,00017/10/2016Nguyen T Thuy Lien giup MS 2317100,00017/10/2016Nguyen T Phuong giup MS 2317150,00017/10/2016Nguyen T Theu giup MS 22931,000,00017/10/2016Nguyen T Huyen ung ho QNA100,00017/10/2016Nguyen T Lien giup MS 2318200,00017/10/2016Nguyen Van Tung giup MS 2318200,00017/10/2016Le T Nga giup MS 2318100,00017/10/2016Nguyen T Kim Anh giup MS 21969,000,00017/10/2016Doan T Thanh Nu giup MS 2318100,00017/10/2016Mai T Ngan giup MS 2313200,00017/10/2016Vo Hoang Hung giup MS 2318100,00017/10/2016Tran Thanh Nga Nhat giup MS 231650,00017/10/2016Tran Thanh Nga Nhat giup MS 231750,00017/10/2016Tran Thanh Nga Nhat giup MS 231850,00017/10/2016Ta T Khanh Hoa giup MS 2318200,00017/10/2016Tran T Kim Thanh giup MS 2317500,00018/10/2016Nguyen Ngoc Lan giup MS 2318100,00018/10/2016Nguyen Van Luyen giup MS 231850,00018/10/2016Nguyen Hung Anh giup MS 23185,000,00018/10/2016Trinh Huu Tu Tran giup MS 23191,000,00018/10/2016Tran Vinh Khuyen giup MS 2319200,00018/10/2016Doan Dinh Phuc giup MS 23191,000,00018/10/2016Nguyen Huu Dinh giup MS 2319100,00018/10/2016Ngo Phuong Thao giup MS 2319100,00018/10/2016Doan T Thanh Nu giup MS 2319100,00018/10/2016Hoang Dinh Duc giup MS 231950,00018/10/2016Pham Duc Chinh giup MS 2318500,00018/10/2016Nguyen T Hien ung ho QNA200,00018/10/2016Nguyen T Thuy Ha giup MS 2319500,00018/10/2016Tran T Nhi giup MS 2320300,00018/10/2016Duong T Kim Lien giup MS 2319200,00018/10/2016Mai Thu Hang giup MS 2319500,00018/10/2016Duong T Kim Lien giup MS 2318200,00018/10/2016Vo T Huyen giup MS 2319200,00018/10/2016Dong T Kim Nen giup MS 2319500,00018/10/2016Le Thai Ha giup Ms 2320500,00019/10/2016Nguyen Trong Nghia giup MS 2319100,00019/10/2016Luu Van Thong ung ho QNA1,000,00019/10/2016Nguyen Manh Cuong giup MS 2320500,00019/10/2016Do T Thanh Thao giup MS 23191,000,00019/10/2016Do T Thanh Thao giup MS 23211,000,00019/10/2016Nguyen Thanh Binh ung ho QNA500,00019/10/2016Vu T Hien giup MS 2320100,00019/10/2016Vu T Hao + Vu T Hieu giup MS 2319200,00019/10/2016Phan Vu Ninh ung ho QNA500,00019/10/2016Nguyen T Hong Van giup MS 2320500,00019/10/2016Doan Huong Duong giup MS 2321100,00019/10/2016Doan Huong Duong giup MS 2319100,00019/10/2016Le T Thanh Nga EM giup MS 2320100,00019/10/2016Cao Thanh Trung giup MS 2320200,00019/10/2016Nguyen Minh Thu giup MS 2204100,00019/10/2016Pham Duc Chinh giup MS 2320200,00019/10/2016Vo Hoang Hung giup M S2320200,00019/10/2016Nguyen Huu Phuc giup MS 2306500,00019/10/2016Nguyen Huu Phuc giup MS 2313500,00019/10/2016Nguyen Huu Phuc giup MS 2315500,00019/10/2016Nguyen Huu Phuc giup MS 2311500,00020/10/2016Le Van Thanh giup MS 2320200,00020/10/2016Ma Xuan Bach ung ho QNA300,00020/10/2016Nguyen Phuoc Ngoc giup MS 23201,000,00020/10/2016Cty CNL tru HT giup MS 23202,000,00020/10/2016Nguyen T Thanh Thuy giup MS 23201,000,00020/10/2016Lop 10C9 truong THPT Nguyen Trai , An Duong, Hai Phong giup MS 2320600,00020/10/2016Tong T Ngoc Han giup MS 2320200,00020/10/2016Dinh Hung Cuong giup MS 23201,000,00020/10/2016Pham T Cuc giup MS 2319500,00020/10/2016Luong T Thu giup MS 2320200,00020/10/2016Nguyen Huu Hoan giup MS 2320100,00020/10/2016Le T Thuy giup MS 23202,000,00020/10/2016Pham T Huyen Trang giup MS 2320200,00020/10/2016Nguyen T Lan giup MS 2320200,00020/10/2016Nguyen T Kiep giup MS 23201,000,00020/10/2016Duong Huong Duong giup MS 2316100,00020/10/2016Duong Huong Duong giup MS 2318100,00020/10/2016Duong Huong Duong giup MS 2317100,00020/10/2016Duong Huong Duong giup MS 2322100,00021/10/2016Nguyen T Thuy Lien giup MS 2322100,00021/10/2016Nguyen T Thuy giup MS 2323200,00021/10/2016Bui T Hoa giup MS 23126,500,00021/10/2016Phan T Viet giup MS 23203,200,00021/10/2016Hoang Van Thuy giup MS 2320200,00021/10/2016Tran VAn Thach ung ho QNA500,00021/10/2016Dang T Ngoc Lan giup MS 23231,000,00021/10/2016Doan Tran Ngoc Quynh giup MS 2323100,00021/10/2016Thai Tan Xuyen giup MS 2318300,00021/10/2016Tran Huy Khanh giup MS 2320500,00021/10/2016Lac Hong Minh giup MS 2294100,00021/10/2016Lac Hong Minh giup MS 2299100,00021/10/2016Lac Hong Minh giup MS 2304100,00021/10/2016Lac Hong Minh giup MS 2305100,00021/10/2016Lac Hong Minh giup MS 2315100,00021/10/2016Lac Hong Minh giup MS 2319100,00021/10/2016Lac Hong Minh giup MS 2303200,00021/10/2016Lac Hong Minh giup MS 2313200,00021/10/2016Ha Quoc Binh giup MS 23201,000,00022/10/2016Le T My Hanh giup MS 2319200,00022/10/2016Phan Xuan Thanh ung ho QNA100,00022/10/2016Trinh Van Nhang giup MS 2323200,00022/10/2016Le Van Giang giup MS 2320300,000 Bạn đọc ủng hộ qua ngân hàng BIDV\n\t\t\ttừ ngày 16 đến 22/10/2016 16/10/2016Pham Minh Tri giup MS 2315200,00016/10/2016Ban doc TK 57010000432927 giup MS 231150,00017/10/2016Duong Van Hao giup MS 2318100,00017/10/2016Le T Hoi giup MS 2318100,00017/10/2016Nguyen Van Quang giup MS 2313200,00017/10/2016Nguyen T Thu Huyen giup MS 2318500,00017/10/2016Sunny giup MS 2318300,00017/10/2016Pham Anh Duc giup MS 2317300,00017/10/2016Pham Anh Duc giup MS 2318300,00017/10/2016Ban doc TK 21110000374298 giup MS 2318100,00017/10/2016Vu Hai Ha giup MS 2313500,00017/10/2016Vu Hai Ha giup MS 2317500,00017/10/2016Nguyen To Dung giup MS 2307300,00017/10/2016Nguyen To Dung giup MS 2311300,00017/10/2016Nguyen To Dung giup MS 2312300,00017/10/2016Nguyen To Dung giup MS 2313300,00017/10/2016Nguyen To Dung giup MS 2314300,00017/10/2016Nguyen To Dung giup MS 2317300,00017/10/2016Nguyen To Dung giup MS 2318300,00017/10/2016Nguyen T Hong Hoa giup MS 2318200,00017/10/2016Nguyen Van Hoa giup MS 2317100,00017/10/2016Ban doc TK 035704060071034 giup MS 2318100,00017/10/2016Tran T Thanh Thuy giup MS 2318200,00017/10/2016Pham Viet Dung giup MS 2318250,00017/10/2016Nguyen Dinh giup MS 231810,00017/10/2016Nguyen Dinh giup MS 230910,00017/10/2016Nguyen Dinh giup MS 227610,00017/10/2016Nguyen Dinh giup MS 226410,00017/10/2016Nguyen Dinh giup MS 223110,00017/10/2016Hoang Cao Thang giup MS 2318100,00018/10/2016Pham Minh Tri giup MS 2318200,00018/10/2016Nguyen Phuong Hai giup MS 2319200,00018/10/2016Pham T Hien giup MS 2319300,00018/10/2016Do T Lan Huong giup MS 2319300,00018/10/2016Nguyen Huu Chi giup MS 2194100,00018/10/2016Dinh Thanh Son giup MS 2319500,00018/10/2016Nguyen Huu Chi giup MS 2201100,00018/10/2016Nguyen T Ngoc Vui giup MS 2319500,00018/10/2016Ban doc TK 01100013625258 giup MS 2319200,00018/10/2016Pham T Thanh Thuy giup MS 2319200,00018/10/2016Ho Duc Thang giup MS 2319200,00018/10/2016Dao Vu Thinh Van giup MS 2319300,00018/10/2016Pham Quang Hung giup MS 2319200,00018/10/2016Dao Quang Khai giup MS 2319500,00018/10/2016Mai The Chuyen giup MS 231250,00018/10/2016Mai The Chuyen giup MS 231750,00018/10/2016Mai The Chuyen giup MS 231950,00018/10/2016Luu T Anh Tuyet giup MS 2319200,00018/10/2016Doan Tran Minh giup MS 2319300,00018/10/2016Tran Minh Lan giup MS 2319200,00018/10/2016Vu T Hang giup MS 2319100,00018/10/2016Ban doc TK 1001676872 giup MS 2319400,00018/10/2016Ban doc TK 12010000296964100,00018/10/2016Vu T Quyen giup MS 2319300,00018/10/2016Nguyen Hoang Anh giup MS 231980,00018/10/2016Nguyen Manh Trung giup MS 2319500,00018/10/2016Nguyen T Thuy giup MS 2319300,00018/10/2016Le T Thanh Huong giup MS 2320200,00018/10/2016Tran Quyet Thang giup MS 23220100,00018/10/2016Tran Hoai Nam giup MS 2320500,00018/10/2016Mai Thanh Ha giup MS 2319200,00018/10/2016Vu Tien Dung giup MS 2320100,00018/10/2016Gia dinh Trung Tuyet giup MS 2320200,00018/10/2016Mai Thanh Ha giup MS 2320200,00018/10/2016Mai Thanh Ha giup MS 2318200,00019/10/2016Pham Nam Duong giup MS 2320200,00019/10/2016Dinh Thuy Lan giup MS 2295100,00019/10/2016Dinh Thuy Lan giup MS 2296100,00019/10/2016Dinh Thuy Lan giup MS 2297100,00019/10/2016Dinh Thuy Lan giup MS 2298100,00019/10/2016Dinh Thuy Lan giup MS 2299100,00019/10/2016Dinh Thuy Lan giup MS 2300100,00019/10/2016Dinh Thuy Lan giup MS 2301100,00019/10/2016Dinh Thuy Lan giup MS 2302100,00019/10/2016Dinh Thuy Lan giup MS 2303100,00019/10/2016Dinh Thuy Lan giup MS 2304100,00019/10/2016Dinh Thuy Lan giup MS 2305100,00019/10/2016Dinh Thuy Lan giup MS 2306100,00019/10/2016Dinh Thuy Lan giup MS 2307100,00019/10/2016Dinh Thuy Lan giup MS 2308100,00019/10/2016Dinh Thuy Lan giup MS 2309100,00019/10/2016Dinh Thuy Lan giup MS 2310100,00019/10/2016Dinh Thuy Lan giup MS 2311100,00019/10/2016Dinh Thuy Lan giup MS 2312100,00019/10/2016Dinh Thuy Lan giup MS 2313100,00019/10/2016Dinh Thuy Lan giup MS 2314100,00019/10/2016Dinh Thuy Lan giup MS 2315100,00019/10/2016Dinh Thuy Lan giup MS 2316100,00019/10/2016Dinh Thuy Lan giup MS 2317100,00019/10/2016Dinh Thuy Lan giup MS 2318100,00019/10/2016Dinh Thuy Lan giup MS 2319100,00019/10/2016Ban doc TK 1002247491 giup MS 2319500,00019/10/2016Ban doc TK 22210002059999 giup MS 2320300,00019/10/2016Do T Lan Huong giup MS 2320360,00019/10/2016Pham Viet Lan Anh giup MS 2319500,00019/10/2016Ban doc so dien thoai 0914151581 giup MS 2301200,00019/10/2016Ban doc so dien thoai 0914151581 giup MS 2319200,00019/10/2016Tran T Thanh Huong giup MS 23111,000,00019/10/2016Ngo Van Hien giup MS 2320300,00019/10/2016Nguyen Van Hung giup MS 2320300,00019/10/2016Nguyen T Tuyet giup MS 2319100,00019/10/2016Nguyen Van Loi giup MS 2318100,00019/10/2016Nguyen Linh San giup MS 2317100,00019/10/2016Nguyen T Lan Huong giup MS 2320100,00019/10/2016Ban doc TK 67010000092047 ung ho QNA300,00019/10/2016Ban doc TK 17111982001 giup MS 23202,000,00019/10/2016Ban doc Dan tri giup MS 2320500,00019/10/2016Ban doc TK 056704060021534 giup MS 2320300,00019/10/2016Vu T Khuong giup MS 2321500,00019/10/2016Ban doc TK 58210000005061 giup MS 2320200,00019/10/2016Ban do c Dan tri giup MS 2319150,00019/10/2016Ban do c Dan tri giup MS 2320150,00019/10/2016Doan Thu Thuy giup MS 2320500,00019/10/2016Doan Thu Thuy giup MS 2320500,00019/10/2016Tran T Loan giup MS 2320200,00019/10/2016Le T Hong Tam giup MS 2320200,00019/10/2016Cty TNHH Cong nghe Hoang Bao Quan giup MS 22221,000,00019/10/2016Mai Thanh Ha giup MS 2321200,00019/10/2016Ban doc TK 12510000521324 giup MS 2320200,00019/10/2016Ban doc TK 1030101017756868 giup MS 232190,00019/10/2016Ban doc TK 39010000190579 ung ho QNA200,00019/10/2016Ban doc TK 39010000191235 ung ho 2320100,00019/10/2016Ban doc Dan tri giup MS 2320500,00020/10/2016Hoang Van Su giup MS 2320500,00020/10/2016Nguyen Hong Quan giup MS 23201,000,00020/10/2016Duong Van Viet giup MS 2319300,00020/10/2016Phung Quang Thanh giup MS 2320300,00020/10/2016Nong Lan Phuong giup MS 2320200,00020/10/2016Nguyen T Huong Truc giup Ms 2319500,00020/10/2016Ban doc TK 21210000341581 ung ho QNA300,00020/10/2016Ban doc TK 21410000708357 ung ho QNA500,00020/10/2016Ban doc TK 2160000281205 giup MS 2320500,00020/10/2016Bui Tuan Sinh giup MS 23201,000,00020/10/2016Nguyen Hong Nhung giup MS 23201,000,00020/10/2016Nguyen Hong Nhung giup MS 2321500,00020/10/2016Mai Thanh Ha giup MS 2322200,00020/10/2016Nguyen Dinh Tam giup MS 2322200,00020/10/2016Tran Ngoc Duc giup MS 2322200,00020/10/2016Pham Minh Tri giup MS 2322200,00021/10/2016Nguyen Minh Quan + Ho Thanh Tam giup MS 23201,000,00021/10/2016Ha Manh Tuong giup MS 2323200,00021/10/2016Ban doc TK 65110001179795 giup MS 2323300,00021/10/2016Pham Duc Tuan giup MS 2323500,00021/10/2016Mai T Hoai Phuong giup MS 2323300,00021/10/2016Nguyen Van Tu ung ho QNA200,00021/10/2016Tran Ngoc Vinh giup MS 2323100,00021/10/2016Ban doc Dan tri ung ho QNA1,000,00021/10/2016Nguyen Manh Hung giup MS 2323100,00021/10/2016Ban doc Dan tri giup MS 23201,000,00021/10/2016Ban doc TK 21110000975202 giup MS 2319200,00021/10/2016Ban doc TK 21110000975202 giup MS 2323100,00021/10/2016Dinh T Thanh Huyen giup MS 2323200,00021/10/2016Le T Hoi giup MS 2323100,00021/10/2016Doan Thu Ha + Trieu Quang Van Toronto Canada giup MS 23205,000,00021/10/2016Doan Thanh nien - Tong Cty Cong trinh Giao thong I Thanh Hoa giup MS 232010,000,00021/10/2016Nguyen T Kim Thanh giup MS 2323500,00021/10/2016Nguyen Dinh Chi giup MS 232398,90021/10/2016Ban doc TK 21110000458484 giup MS 2323400,00021/10/2016Trinh Viet Linh giup MS 2323700,00021/10/2016Thuy Oanh giup MS 23191,000,00021/10/2016Le Van Tan giup MS 2323300,00021/10/2016Lam T Thu Lan giup MS 2323500,00021/10/2016Nguyen Hoan Chau giup MS 2320500,00021/10/2016Do Thai Son giup MS 2323500,00021/10/2016Nguyen T Mai giup MS 23202,000,00022/10/2016Bui Dai Thang giup MS 2323500,00022/10/2016Nguyen T Quynh Trang giup MS 23191,000,00022/10/2016Ngo Duc Vinh giup MS 2323100,00022/10/2016Truong T Thanh Huy giup MS 2323300,00022/10/2016Ban doc TK 62310000125684 giup MS 23231,000,00022/10/2016Dang Huy Liem giup MS 232350,00022/10/2016Dao Quang Khai giup MS 2323300,00022/10/2016Ta Thanh Huyen giup MS 2320500,00022/10/2016Le Trong Kien giup MS 232450,00022/10/2016Hoang Thai Chau giup MS 2323198,900 Tổng899,637,990 ",
    "image_url": "",
    "date": "2016-10-26, 21:54:00+00:00",
    "label_general": "Đời sống - Xã hội"
}