{
    "domain": "giadinh.vnexpress.net",
    "code": "49d5eb71d8f9700e916f7d0e5cdab8512e585cdb",
    "title": "Cả nhà nô đùa bên hồ bơi",
    "url": "http://giadinh.vnexpress.net/tin-tuc/to-am/ca-nha-nang-dong/ca-nha-no-dua-ben-ho-boi-3504990.html",
    "labels": "vnexpress/Gia đình/Tổ ấm/Cuộc thi ảnh cả nhà năng động/Thể lệ/Gửi bài dự thi",
    "content": "\nNguyễn Thị Tuyết Nhung",
    "image_url": "http://img.f16.giadinh.vnecdn.net/2016/11/27/Untitled-2078-1480224032_180x108.png",
    "date": "2016-11-27, 18:27:13+07:00"
}