{
    "domain": "dantri.com.vn",
    "code": "a34388d5a770938d92d1496dd8e7711a1e2623e3",
    "title": "Sét đánh trúng vào máy bay thì có nguy hiểm?",
    "url": "http://dantri.com.vn/khoa-hoc-cong-nghe/set-danh-trung-vao-may-bay-thi-co-nguy-hiem-20161128113856255.htm",
    "labels": "Dân trí/Khoa học - Công nghệ",
    "content": "\nDân trí Mặc dù thực sự đáng sợ khi nghĩ rằng chuyến bay của bạn có thể sẽ bị sét đánh, tuy nhiên trên thực tế, đó lại là điều khá phổ biến. Mỗi năm, một chiếc máy bay sẽ bị sét đánh khoảng 1 lần. Khi đó, đèn chiếu sáng có thể sẽ nhấp nháy, nhưng nhờ vào thiết kế thông minh của máy bay nên mối nguy hiểm rất thấp.\r\nAnh Thư (Theo Businessinsider )",
    "image_url": "https://dantri4.vcmedia.vn/zoom/80_50/2016/setdanh-1480307893964.jpg",
    "date": "2016-11-28, 11:36:00+00:00",
    "label_general": "Khoa học - Công nghệ"
}