{
    "domain": "vnexpress.net",
    "code": "8ea993cb44dbc3a2724829886494fc6d228b9fe4",
    "title": "Nam sinh 'câu' quảng cáo bằng đường link phim, ảnh khiêu dâm",
    "url": "http://vnexpress.net/tin-tuc/phap-luat/nam-sinh-cau-quang-cao-bang-duong-link-phim-anh-khieu-dam-3505450.html",
    "labels": "vnexpress/Pháp luật",
    "content": "\n\tTheo bản án sơ thẩm ngày 28/11 của TAND Hà Nội, năm 2013 Nguyễn Văn Tuyến mở trang web đăng tải các đoạn phim đồi truỵ, hình ảnh khiêu dâm để thu hút người đọc, nhằm thu lợi quảng cáo.\nTính đến tháng 10/2014, trên trang web của Tuyến đã lưu trữ 76 đường dẫn phim từ nước ngoài, 22 bộ ảnh khiêu dâm. Số người truy cập trung bình hơn 140.000, với hàng trăm nghìn lượt xem mỗi ngày. \nTrong khi cơ quan điều tra đang vào cuộc, bị cáo Tuyến đi du học tự túc. Ngày 21/7, người này bị bắt theo lệnh truy nã.\n\tVới hành vi bị khép vào tội Truyền bá văn hoá phẩm đồi truỵ, Tuyến bị phạt 3 năm tù.\nViệt Dũng\n>>'Hoa khôi' công an hạ gục vũ sư đồi trụy\n>>Truyền nhau xem clip sex là phạm tội",
    "image_url": "http://img.f30.vnecdn.net/2016/11/28/Untitled4-1480325787_180x108.jpg",
    "date": "2016-11-28, 16:40:56+07:00"
}