{
    "domain": "vietbao.vn",
    "code": "1a649e6811637234c22e7b1c617b645b6440470e",
    "title": "[Infographic] Những nhầm tưởng về tiết kiệm nhiên liệu của lái xe Việt",
    "url": "http://vietbao.vn/Cong-nghe/Infographic-Nhung-nham-tuong-ve-tiet-kiem-nhien-lieu-cua-lai-xe-Viet/223146273/217/",
    "labels": "vietbao/Công Nghệ/Tin Tổng Hợp",
    "content": "Dựa trên nghiên cứu mới đây về thói quen của các lái xe Việt, Ford Việt Nam đã tổng hợp được những hành vi gây tiêu hao nhiên liệu cũng như đưa ra những lời khuyên để các lái xe có thể thay đổi những thói quen xấu của mình, nâng cao hiệu quả tiêu thụ nhiên liệu cho xe.Theo autopro.com.vnTheo autopro.com.vn",
    "image_url": "http://a9.vietbao.vn/images/vn999/223/2016/11/vietnam_20161129-infographic-nhung-nham-tuong-ve-tiet-kiem-nhi-234-n-lieu-cua-l-225-i-xe-viet-1.jpg",
    "date": "2016-11-29, 08:27:04+07:00"
}